{"firstName": "Vojt\u011bch", "familyName": "Zeithammer", "slug": "sk-slavia-praha-vojtech-zeithammer", "season": "2025-26", "currentTeam": "SK Slavia Praha", "teams": ["SK Slavia Praha"], "seasonTotals": {"pts": 6, "reb": 1, "ast": 6, "stl": 2, "blk": 0, "fgm": 2, "fga": 7, "fg3m": 2, "fg3a": 4, "ftm": 0, "fta": 0, "tov": 3, "pf": 10, "gp": 6, "totalSeconds": 1884.0, "plusMinus": -9}, "seasonAverages": {"minPerGame": "5:14", "pts": 1.0, "reb": 0.2, "ast": 1.0, "stl": 0.3, "blk": 0.0, "fgPct": 28.6, "fg3Pct": 50.0, "ftPct": 0.0, "tov": 0.5, "pf": 1.7, "plusMinus": -1.5}, "games": [{"gameId": "2782893", "date": "2025-12-20", "teamCode": "SKS", "teamName": "SK Slavia Praha", "opponent": "Sr\u0161ni Photomate P\u00edsek", "isHome": true, "score": "73:82", "numOT": 0, "isDNP": false, "totalSeconds": 154, "periods": [{"period": 1, "label": "Q1", "startMinute": 0, "endMinute": 10, "duration": 10}, {"period": 2, "label": "Q2", "startMinute": 10, "endMinute": 20, "duration": 10}, {"period": 3, "label": "Q3", "startMinute": 20, "endMinute": 30, "duration": 10}, {"period": 4, "label": "Q4", "startMinute": 30, "endMinute": 40, "duration": 10}], "minutes": [{"minute": 0, "onCourt": false, "fullMinute": false, "onCourtSeconds": 0.0, "plusMinus": 0, "pts": 0, "stats": {"pts": 0, "reb": 0, "ast": 0, "stl": 0, "blk": 0, "fgm": 0, "fga": 0, "fg3m": 0, "fg3a": 0, "ftm": 0, "fta": 0, "pf": 0, "tov": 0}}, {"minute": 1, "onCourt": false, "fullMinute": false, "onCourtSeconds": 0.0, "plusMinus": 0, "pts": 0, "stats": {"pts": 0, "reb": 0, "ast": 0, "stl": 0, "blk": 0, "fgm": 0, "fga": 0, "fg3m": 0, "fg3a": 0, "ftm": 0, "fta": 0, "pf": 0, "tov": 0}}, {"minute": 2, "onCourt": false, "fullMinute": false, "onCourtSeconds": 0.0, "plusMinus": 0, "pts": 0, "stats": {"pts": 0, "reb": 0, "ast": 0, "stl": 0, "blk": 0, "fgm": 0, "fga": 0, "fg3m": 0, "fg3a": 0, "ftm": 0, "fta": 0, "pf": 0, "tov": 0}}, {"minute": 3, "onCourt": false, "fullMinute": false, "onCourtSeconds": 0.0, "plusMinus": 0, "pts": 0, "stats": {"pts": 0, "reb": 0, "ast": 0, "stl": 0, "blk": 0, "fgm": 0, "fga": 0, "fg3m": 0, "fg3a": 0, "ftm": 0, "fta": 0, "pf": 0, "tov": 0}}, {"minute": 4, "onCourt": false, "fullMinute": false, "onCourtSeconds": 0.0, "plusMinus": 0, "pts": 0, "stats": {"pts": 0, "reb": 0, "ast": 0, "stl": 0, "blk": 0, "fgm": 0, "fga": 0, "fg3m": 0, "fg3a": 0, "ftm": 0, "fta": 0, "pf": 0, "tov": 0}}, {"minute": 5, "onCourt": false, "fullMinute": false, "onCourtSeconds": 0.0, "plusMinus": 0, "pts": 0, "stats": {"pts": 0, "reb": 0, "ast": 0, "stl": 0, "blk": 0, "fgm": 0, "fga": 0, "fg3m": 0, "fg3a": 0, "ftm": 0, "fta": 0, "pf": 0, "tov": 0}}, {"minute": 6, "onCourt": false, "fullMinute": false, "onCourtSeconds": 0.0, "plusMinus": 0, "pts": 0, "stats": {"pts": 0, "reb": 0, "ast": 0, "stl": 0, "blk": 0, "fgm": 0, "fga": 0, "fg3m": 0, "fg3a": 0, "ftm": 0, "fta": 0, "pf": 0, "tov": 0}}, {"minute": 7, "onCourt": true, "fullMinute": false, "onCourtSeconds": 49.0, "plusMinus": 3, "pts": 0, "stats": {"pts": 0, "reb": 0, "ast": 1, "stl": 0, "blk": 0, "fgm": 0, "fga": 0, "fg3m": 0, "fg3a": 0, "ftm": 0, "fta": 0, "pf": 0, "tov": 0}}, {"minute": 8, "onCourt": true, "fullMinute": true, "onCourtSeconds": 60.0, "plusMinus": -4, "pts": 0, "stats": {"pts": 0, "reb": 0, "ast": 0, "stl": 0, "blk": 0, "fgm": 0, "fga": 1, "fg3m": 0, "fg3a": 1, "ftm": 0, "fta": 0, "pf": 1, "tov": 0}}, {"minute": 9, "onCourt": true, "fullMinute": false, "onCourtSeconds": 44.0, "plusMinus": -2, "pts": 0, "stats": {"pts": 0, "reb": 0, "ast": 0, "stl": 0, "blk": 0, "fgm": 0, "fga": 0, "fg3m": 0, "fg3a": 0, "ftm": 0, "fta": 0, "pf": 0, "tov": 2}}, {"minute": 10, "onCourt": false, "fullMinute": false, "onCourtSeconds": 0.0, "plusMinus": 0, "pts": 0, "stats": {"pts": 0, "reb": 0, "ast": 0, "stl": 0, "blk": 0, "fgm": 0, "fga": 0, "fg3m": 0, "fg3a": 0, "ftm": 0, "fta": 0, "pf": 0, "tov": 0}}, {"minute": 11, "onCourt": false, "fullMinute": false, "onCourtSeconds": 0.0, "plusMinus": 0, "pts": 0, "stats": {"pts": 0, "reb": 0, "ast": 0, "stl": 0, "blk": 0, "fgm": 0, "fga": 0, "fg3m": 0, "fg3a": 0, "ftm": 0, "fta": 0, "pf": 0, "tov": 0}}, {"minute": 12, "onCourt": false, "fullMinute": false, "onCourtSeconds": 0.0, "plusMinus": 0, "pts": 0, "stats": {"pts": 0, "reb": 0, "ast": 0, "stl": 0, "blk": 0, "fgm": 0, "fga": 0, "fg3m": 0, "fg3a": 0, "ftm": 0, "fta": 0, "pf": 0, "tov": 0}}, {"minute": 13, "onCourt": false, "fullMinute": false, "onCourtSeconds": 0.0, "plusMinus": 0, "pts": 0, "stats": {"pts": 0, "reb": 0, "ast": 0, "stl": 0, "blk": 0, "fgm": 0, "fga": 0, "fg3m": 0, "fg3a": 0, "ftm": 0, "fta": 0, "pf": 0, "tov": 0}}, {"minute": 14, "onCourt": false, "fullMinute": false, "onCourtSeconds": 0.0, "plusMinus": 0, "pts": 0, "stats": {"pts": 0, "reb": 0, "ast": 0, "stl": 0, "blk": 0, "fgm": 0, "fga": 0, "fg3m": 0, "fg3a": 0, "ftm": 0, "fta": 0, "pf": 0, "tov": 0}}, {"minute": 15, "onCourt": false, "fullMinute": false, "onCourtSeconds": 0.0, "plusMinus": 0, "pts": 0, "stats": {"pts": 0, "reb": 0, "ast": 0, "stl": 0, "blk": 0, "fgm": 0, "fga": 0, "fg3m": 0, "fg3a": 0, "ftm": 0, "fta": 0, "pf": 0, "tov": 0}}, {"minute": 16, "onCourt": false, "fullMinute": false, "onCourtSeconds": 0.0, "plusMinus": 0, "pts": 0, "stats": {"pts": 0, "reb": 0, "ast": 0, "stl": 0, "blk": 0, "fgm": 0, "fga": 0, "fg3m": 0, "fg3a": 0, "ftm": 0, "fta": 0, "pf": 0, "tov": 0}}, {"minute": 17, "onCourt": false, "fullMinute": false, "onCourtSeconds": 0.0, "plusMinus": 0, "pts": 0, "stats": {"pts": 0, "reb": 0, "ast": 0, "stl": 0, "blk": 0, "fgm": 0, "fga": 0, "fg3m": 0, "fg3a": 0, "ftm": 0, "fta": 0, "pf": 0, "tov": 0}}, {"minute": 18, "onCourt": false, "fullMinute": false, "onCourtSeconds": 0.0, "plusMinus": 0, "pts": 0, "stats": {"pts": 0, "reb": 0, "ast": 0, "stl": 0, "blk": 0, "fgm": 0, "fga": 0, "fg3m": 0, "fg3a": 0, "ftm": 0, "fta": 0, "pf": 0, "tov": 0}}, {"minute": 19, "onCourt": false, "fullMinute": false, "onCourtSeconds": 0.0, "plusMinus": 0, "pts": 0, "stats": {"pts": 0, "reb": 0, "ast": 0, "stl": 0, "blk": 0, "fgm": 0, "fga": 0, "fg3m": 0, "fg3a": 0, "ftm": 0, "fta": 0, "pf": 0, "tov": 0}}, {"minute": 20, "onCourt": false, "fullMinute": false, "onCourtSeconds": 0.0, "plusMinus": 0, "pts": 0, "stats": {"pts": 0, "reb": 0, "ast": 0, "stl": 0, "blk": 0, "fgm": 0, "fga": 0, "fg3m": 0, "fg3a": 0, "ftm": 0, "fta": 0, "pf": 0, "tov": 0}}, {"minute": 21, "onCourt": false, "fullMinute": false, "onCourtSeconds": 0.0, "plusMinus": 0, "pts": 0, "stats": {"pts": 0, "reb": 0, "ast": 0, "stl": 0, "blk": 0, "fgm": 0, "fga": 0, "fg3m": 0, "fg3a": 0, "ftm": 0, "fta": 0, "pf": 0, "tov": 0}}, {"minute": 22, "onCourt": false, "fullMinute": false, "onCourtSeconds": 0.0, "plusMinus": 0, "pts": 0, "stats": {"pts": 0, "reb": 0, "ast": 0, "stl": 0, "blk": 0, "fgm": 0, "fga": 0, "fg3m": 0, "fg3a": 0, "ftm": 0, "fta": 0, "pf": 0, "tov": 0}}, {"minute": 23, "onCourt": false, "fullMinute": false, "onCourtSeconds": 0.0, "plusMinus": 0, "pts": 0, "stats": {"pts": 0, "reb": 0, "ast": 0, "stl": 0, "blk": 0, "fgm": 0, "fga": 0, "fg3m": 0, "fg3a": 0, "ftm": 0, "fta": 0, "pf": 0, "tov": 0}}, {"minute": 24, "onCourt": false, "fullMinute": false, "onCourtSeconds": 0.0, "plusMinus": 0, "pts": 0, "stats": {"pts": 0, "reb": 0, "ast": 0, "stl": 0, "blk": 0, "fgm": 0, "fga": 0, "fg3m": 0, "fg3a": 0, "ftm": 0, "fta": 0, "pf": 0, "tov": 0}}, {"minute": 25, "onCourt": false, "fullMinute": false, "onCourtSeconds": 0.0, "plusMinus": 0, "pts": 0, "stats": {"pts": 0, "reb": 0, "ast": 0, "stl": 0, "blk": 0, "fgm": 0, "fga": 0, "fg3m": 0, "fg3a": 0, "ftm": 0, "fta": 0, "pf": 0, "tov": 0}}, {"minute": 26, "onCourt": false, "fullMinute": false, "onCourtSeconds": 0.0, "plusMinus": 0, "pts": 0, "stats": {"pts": 0, "reb": 0, "ast": 0, "stl": 0, "blk": 0, "fgm": 0, "fga": 0, "fg3m": 0, "fg3a": 0, "ftm": 0, "fta": 0, "pf": 0, "tov": 0}}, {"minute": 27, "onCourt": false, "fullMinute": false, "onCourtSeconds": 0.0, "plusMinus": 0, "pts": 0, "stats": {"pts": 0, "reb": 0, "ast": 0, "stl": 0, "blk": 0, "fgm": 0, "fga": 0, "fg3m": 0, "fg3a": 0, "ftm": 0, "fta": 0, "pf": 0, "tov": 0}}, {"minute": 28, "onCourt": false, "fullMinute": false, "onCourtSeconds": 0.0, "plusMinus": 0, "pts": 0, "stats": {"pts": 0, "reb": 0, "ast": 0, "stl": 0, "blk": 0, "fgm": 0, "fga": 0, "fg3m": 0, "fg3a": 0, "ftm": 0, "fta": 0, "pf": 0, "tov": 0}}, {"minute": 29, "onCourt": false, "fullMinute": false, "onCourtSeconds": 0.0, "plusMinus": 0, "pts": 0, "stats": {"pts": 0, "reb": 0, "ast": 0, "stl": 0, "blk": 0, "fgm": 0, "fga": 0, "fg3m": 0, "fg3a": 0, "ftm": 0, "fta": 0, "pf": 0, "tov": 0}}, {"minute": 30, "onCourt": false, "fullMinute": false, "onCourtSeconds": 0.0, "plusMinus": 0, "pts": 0, "stats": {"pts": 0, "reb": 0, "ast": 0, "stl": 0, "blk": 0, "fgm": 0, "fga": 0, "fg3m": 0, "fg3a": 0, "ftm": 0, "fta": 0, "pf": 0, "tov": 0}}, {"minute": 31, "onCourt": false, "fullMinute": false, "onCourtSeconds": 0.0, "plusMinus": 0, "pts": 0, "stats": {"pts": 0, "reb": 0, "ast": 0, "stl": 0, "blk": 0, "fgm": 0, "fga": 0, "fg3m": 0, "fg3a": 0, "ftm": 0, "fta": 0, "pf": 0, "tov": 0}}, {"minute": 32, "onCourt": false, "fullMinute": false, "onCourtSeconds": 0.0, "plusMinus": 0, "pts": 0, "stats": {"pts": 0, "reb": 0, "ast": 0, "stl": 0, "blk": 0, "fgm": 0, "fga": 0, "fg3m": 0, "fg3a": 0, "ftm": 0, "fta": 0, "pf": 0, "tov": 0}}, {"minute": 33, "onCourt": false, "fullMinute": false, "onCourtSeconds": 0.0, "plusMinus": 0, "pts": 0, "stats": {"pts": 0, "reb": 0, "ast": 0, "stl": 0, "blk": 0, "fgm": 0, "fga": 0, "fg3m": 0, "fg3a": 0, "ftm": 0, "fta": 0, "pf": 0, "tov": 0}}, {"minute": 34, "onCourt": false, "fullMinute": false, "onCourtSeconds": 0.0, "plusMinus": 0, "pts": 0, "stats": {"pts": 0, "reb": 0, "ast": 0, "stl": 0, "blk": 0, "fgm": 0, "fga": 0, "fg3m": 0, "fg3a": 0, "ftm": 0, "fta": 0, "pf": 0, "tov": 0}}, {"minute": 35, "onCourt": false, "fullMinute": false, "onCourtSeconds": 0.0, "plusMinus": 0, "pts": 0, "stats": {"pts": 0, "reb": 0, "ast": 0, "stl": 0, "blk": 0, "fgm": 0, "fga": 0, "fg3m": 0, "fg3a": 0, "ftm": 0, "fta": 0, "pf": 0, "tov": 0}}, {"minute": 36, "onCourt": false, "fullMinute": false, "onCourtSeconds": 0.0, "plusMinus": 0, "pts": 0, "stats": {"pts": 0, "reb": 0, "ast": 0, "stl": 0, "blk": 0, "fgm": 0, "fga": 0, "fg3m": 0, "fg3a": 0, "ftm": 0, "fta": 0, "pf": 0, "tov": 0}}, {"minute": 37, "onCourt": false, "fullMinute": false, "onCourtSeconds": 0.0, "plusMinus": 0, "pts": 0, "stats": {"pts": 0, "reb": 0, "ast": 0, "stl": 0, "blk": 0, "fgm": 0, "fga": 0, "fg3m": 0, "fg3a": 0, "ftm": 0, "fta": 0, "pf": 0, "tov": 0}}, {"minute": 38, "onCourt": false, "fullMinute": false, "onCourtSeconds": 0.0, "plusMinus": 0, "pts": 0, "stats": {"pts": 0, "reb": 0, "ast": 0, "stl": 0, "blk": 0, "fgm": 0, "fga": 0, "fg3m": 0, "fg3a": 0, "ftm": 0, "fta": 0, "pf": 0, "tov": 0}}, {"minute": 39, "onCourt": true, "fullMinute": false, "onCourtSeconds": 1.0, "plusMinus": 1, "pts": 0, "stats": {"pts": 0, "reb": 0, "ast": 0, "stl": 0, "blk": 0, "fgm": 0, "fga": 0, "fg3m": 0, "fg3a": 0, "ftm": 0, "fta": 0, "pf": 0, "tov": 0}}], "gameStats": {"pts": 0, "reb": 0, "ast": 1, "stl": 0, "blk": 0, "fgm": 0, "fga": 1, "fg3m": 0, "fg3a": 1, "ftm": 0, "fta": 0, "pf": 2, "tov": 2}, "totalPlusMinus": -2}, {"gameId": "2787026", "date": "2025-12-27", "teamCode": "SKS", "teamName": "SK Slavia Praha", "opponent": "BK Olomoucko", "isHome": false, "score": "84:90", "numOT": 0, "isDNP": true, "totalSeconds": 0, "periods": [{"period": 1, "label": "Q1", "startMinute": 0, "endMinute": 10, "duration": 10}, {"period": 2, "label": "Q2", "startMinute": 10, "endMinute": 20, "duration": 10}, {"period": 3, "label": "Q3", "startMinute": 20, "endMinute": 30, "duration": 10}, {"period": 4, "label": "Q4", "startMinute": 30, "endMinute": 40, "duration": 10}], "minutes": [], "gameStats": {"pts": 0, "reb": 0, "ast": 0, "stl": 0, "blk": 0, "fgm": 0, "fga": 0, "fg3m": 0, "fg3a": 0, "ftm": 0, "fta": 0, "pf": 0, "tov": 0}, "totalPlusMinus": 0}, {"gameId": "2787960", "date": "2025-12-30", "teamCode": "SKS", "teamName": "SK Slavia Praha", "opponent": "BK Opava", "isHome": true, "score": "93:98", "numOT": 0, "isDNP": true, "totalSeconds": 0, "periods": [{"period": 1, "label": "Q1", "startMinute": 0, "endMinute": 10, "duration": 10}, {"period": 2, "label": "Q2", "startMinute": 10, "endMinute": 20, "duration": 10}, {"period": 3, "label": "Q3", "startMinute": 20, "endMinute": 30, "duration": 10}, {"period": 4, "label": "Q4", "startMinute": 30, "endMinute": 40, "duration": 10}], "minutes": [], "gameStats": {"pts": 0, "reb": 0, "ast": 0, "stl": 0, "blk": 0, "fgm": 0, "fga": 0, "fg3m": 0, "fg3a": 0, "ftm": 0, "fta": 0, "pf": 0, "tov": 0}, "totalPlusMinus": 0}, {"gameId": "2789897", "date": "2026-01-04", "teamCode": "SKS", "teamName": "SK Slavia Praha", "opponent": "SLUNETA  \u00dast\u00ed nad Labem", "isHome": true, "score": "86:107", "numOT": 0, "isDNP": false, "totalSeconds": 356.0, "periods": [{"period": 1, "label": "Q1", "startMinute": 0, "endMinute": 10, "duration": 10}, {"period": 2, "label": "Q2", "startMinute": 10, "endMinute": 20, "duration": 10}, {"period": 3, "label": "Q3", "startMinute": 20, "endMinute": 30, "duration": 10}, {"period": 4, "label": "Q4", "startMinute": 30, "endMinute": 40, "duration": 10}], "minutes": [{"minute": 0, "onCourt": false, "fullMinute": false, "onCourtSeconds": 0.0, "plusMinus": 0, "pts": 0, "stats": {"pts": 0, "reb": 0, "ast": 0, "stl": 0, "blk": 0, "fgm": 0, "fga": 0, "fg3m": 0, "fg3a": 0, "ftm": 0, "fta": 0, "pf": 0, "tov": 0}}, {"minute": 1, "onCourt": false, "fullMinute": false, "onCourtSeconds": 0.0, "plusMinus": 0, "pts": 0, "stats": {"pts": 0, "reb": 0, "ast": 0, "stl": 0, "blk": 0, "fgm": 0, "fga": 0, "fg3m": 0, "fg3a": 0, "ftm": 0, "fta": 0, "pf": 0, "tov": 0}}, {"minute": 2, "onCourt": false, "fullMinute": false, "onCourtSeconds": 0.0, "plusMinus": 0, "pts": 0, "stats": {"pts": 0, "reb": 0, "ast": 0, "stl": 0, "blk": 0, "fgm": 0, "fga": 0, "fg3m": 0, "fg3a": 0, "ftm": 0, "fta": 0, "pf": 0, "tov": 0}}, {"minute": 3, "onCourt": false, "fullMinute": false, "onCourtSeconds": 0.0, "plusMinus": 0, "pts": 0, "stats": {"pts": 0, "reb": 0, "ast": 0, "stl": 0, "blk": 0, "fgm": 0, "fga": 0, "fg3m": 0, "fg3a": 0, "ftm": 0, "fta": 0, "pf": 0, "tov": 0}}, {"minute": 4, "onCourt": false, "fullMinute": false, "onCourtSeconds": 0.0, "plusMinus": 0, "pts": 0, "stats": {"pts": 0, "reb": 0, "ast": 0, "stl": 0, "blk": 0, "fgm": 0, "fga": 0, "fg3m": 0, "fg3a": 0, "ftm": 0, "fta": 0, "pf": 0, "tov": 0}}, {"minute": 5, "onCourt": false, "fullMinute": false, "onCourtSeconds": 0.0, "plusMinus": 0, "pts": 0, "stats": {"pts": 0, "reb": 0, "ast": 0, "stl": 0, "blk": 0, "fgm": 0, "fga": 0, "fg3m": 0, "fg3a": 0, "ftm": 0, "fta": 0, "pf": 0, "tov": 0}}, {"minute": 6, "onCourt": false, "fullMinute": false, "onCourtSeconds": 0.0, "plusMinus": 0, "pts": 0, "stats": {"pts": 0, "reb": 0, "ast": 0, "stl": 0, "blk": 0, "fgm": 0, "fga": 0, "fg3m": 0, "fg3a": 0, "ftm": 0, "fta": 0, "pf": 0, "tov": 0}}, {"minute": 7, "onCourt": false, "fullMinute": false, "onCourtSeconds": 0.0, "plusMinus": 0, "pts": 0, "stats": {"pts": 0, "reb": 0, "ast": 0, "stl": 0, "blk": 0, "fgm": 0, "fga": 0, "fg3m": 0, "fg3a": 0, "ftm": 0, "fta": 0, "pf": 0, "tov": 0}}, {"minute": 8, "onCourt": false, "fullMinute": false, "onCourtSeconds": 0.0, "plusMinus": 0, "pts": 0, "stats": {"pts": 0, "reb": 0, "ast": 0, "stl": 0, "blk": 0, "fgm": 0, "fga": 0, "fg3m": 0, "fg3a": 0, "ftm": 0, "fta": 0, "pf": 0, "tov": 0}}, {"minute": 9, "onCourt": false, "fullMinute": false, "onCourtSeconds": 0.0, "plusMinus": 0, "pts": 0, "stats": {"pts": 0, "reb": 0, "ast": 0, "stl": 0, "blk": 0, "fgm": 0, "fga": 0, "fg3m": 0, "fg3a": 0, "ftm": 0, "fta": 0, "pf": 0, "tov": 0}}, {"minute": 10, "onCourt": false, "fullMinute": false, "onCourtSeconds": 0.0, "plusMinus": 0, "pts": 0, "stats": {"pts": 0, "reb": 0, "ast": 0, "stl": 0, "blk": 0, "fgm": 0, "fga": 0, "fg3m": 0, "fg3a": 0, "ftm": 0, "fta": 0, "pf": 0, "tov": 0}}, {"minute": 11, "onCourt": false, "fullMinute": false, "onCourtSeconds": 0.0, "plusMinus": 0, "pts": 0, "stats": {"pts": 0, "reb": 0, "ast": 0, "stl": 0, "blk": 0, "fgm": 0, "fga": 0, "fg3m": 0, "fg3a": 0, "ftm": 0, "fta": 0, "pf": 0, "tov": 0}}, {"minute": 12, "onCourt": false, "fullMinute": false, "onCourtSeconds": 0.0, "plusMinus": 0, "pts": 0, "stats": {"pts": 0, "reb": 0, "ast": 0, "stl": 0, "blk": 0, "fgm": 0, "fga": 0, "fg3m": 0, "fg3a": 0, "ftm": 0, "fta": 0, "pf": 0, "tov": 0}}, {"minute": 13, "onCourt": false, "fullMinute": false, "onCourtSeconds": 0.0, "plusMinus": 0, "pts": 0, "stats": {"pts": 0, "reb": 0, "ast": 0, "stl": 0, "blk": 0, "fgm": 0, "fga": 0, "fg3m": 0, "fg3a": 0, "ftm": 0, "fta": 0, "pf": 0, "tov": 0}}, {"minute": 14, "onCourt": false, "fullMinute": false, "onCourtSeconds": 0.0, "plusMinus": 0, "pts": 0, "stats": {"pts": 0, "reb": 0, "ast": 0, "stl": 0, "blk": 0, "fgm": 0, "fga": 0, "fg3m": 0, "fg3a": 0, "ftm": 0, "fta": 0, "pf": 0, "tov": 0}}, {"minute": 15, "onCourt": false, "fullMinute": false, "onCourtSeconds": 0.0, "plusMinus": 0, "pts": 0, "stats": {"pts": 0, "reb": 0, "ast": 0, "stl": 0, "blk": 0, "fgm": 0, "fga": 0, "fg3m": 0, "fg3a": 0, "ftm": 0, "fta": 0, "pf": 0, "tov": 0}}, {"minute": 16, "onCourt": false, "fullMinute": false, "onCourtSeconds": 0.0, "plusMinus": 0, "pts": 0, "stats": {"pts": 0, "reb": 0, "ast": 0, "stl": 0, "blk": 0, "fgm": 0, "fga": 0, "fg3m": 0, "fg3a": 0, "ftm": 0, "fta": 0, "pf": 0, "tov": 0}}, {"minute": 17, "onCourt": false, "fullMinute": false, "onCourtSeconds": 0.0, "plusMinus": 0, "pts": 0, "stats": {"pts": 0, "reb": 0, "ast": 0, "stl": 0, "blk": 0, "fgm": 0, "fga": 0, "fg3m": 0, "fg3a": 0, "ftm": 0, "fta": 0, "pf": 0, "tov": 0}}, {"minute": 18, "onCourt": false, "fullMinute": false, "onCourtSeconds": 0.0, "plusMinus": 0, "pts": 0, "stats": {"pts": 0, "reb": 0, "ast": 0, "stl": 0, "blk": 0, "fgm": 0, "fga": 0, "fg3m": 0, "fg3a": 0, "ftm": 0, "fta": 0, "pf": 0, "tov": 0}}, {"minute": 19, "onCourt": false, "fullMinute": false, "onCourtSeconds": 0.0, "plusMinus": 0, "pts": 0, "stats": {"pts": 0, "reb": 0, "ast": 0, "stl": 0, "blk": 0, "fgm": 0, "fga": 0, "fg3m": 0, "fg3a": 0, "ftm": 0, "fta": 0, "pf": 0, "tov": 0}}, {"minute": 20, "onCourt": false, "fullMinute": false, "onCourtSeconds": 0.0, "plusMinus": 0, "pts": 0, "stats": {"pts": 0, "reb": 0, "ast": 0, "stl": 0, "blk": 0, "fgm": 0, "fga": 0, "fg3m": 0, "fg3a": 0, "ftm": 0, "fta": 0, "pf": 0, "tov": 0}}, {"minute": 21, "onCourt": false, "fullMinute": false, "onCourtSeconds": 0.0, "plusMinus": 0, "pts": 0, "stats": {"pts": 0, "reb": 0, "ast": 0, "stl": 0, "blk": 0, "fgm": 0, "fga": 0, "fg3m": 0, "fg3a": 0, "ftm": 0, "fta": 0, "pf": 0, "tov": 0}}, {"minute": 22, "onCourt": false, "fullMinute": false, "onCourtSeconds": 0.0, "plusMinus": 0, "pts": 0, "stats": {"pts": 0, "reb": 0, "ast": 0, "stl": 0, "blk": 0, "fgm": 0, "fga": 0, "fg3m": 0, "fg3a": 0, "ftm": 0, "fta": 0, "pf": 0, "tov": 0}}, {"minute": 23, "onCourt": false, "fullMinute": false, "onCourtSeconds": 0.0, "plusMinus": 0, "pts": 0, "stats": {"pts": 0, "reb": 0, "ast": 0, "stl": 0, "blk": 0, "fgm": 0, "fga": 0, "fg3m": 0, "fg3a": 0, "ftm": 0, "fta": 0, "pf": 0, "tov": 0}}, {"minute": 24, "onCourt": false, "fullMinute": false, "onCourtSeconds": 0.0, "plusMinus": 0, "pts": 0, "stats": {"pts": 0, "reb": 0, "ast": 0, "stl": 0, "blk": 0, "fgm": 0, "fga": 0, "fg3m": 0, "fg3a": 0, "ftm": 0, "fta": 0, "pf": 0, "tov": 0}}, {"minute": 25, "onCourt": false, "fullMinute": false, "onCourtSeconds": 0.0, "plusMinus": 0, "pts": 0, "stats": {"pts": 0, "reb": 0, "ast": 0, "stl": 0, "blk": 0, "fgm": 0, "fga": 0, "fg3m": 0, "fg3a": 0, "ftm": 0, "fta": 0, "pf": 0, "tov": 0}}, {"minute": 26, "onCourt": false, "fullMinute": false, "onCourtSeconds": 0.0, "plusMinus": 0, "pts": 0, "stats": {"pts": 0, "reb": 0, "ast": 0, "stl": 0, "blk": 0, "fgm": 0, "fga": 0, "fg3m": 0, "fg3a": 0, "ftm": 0, "fta": 0, "pf": 0, "tov": 0}}, {"minute": 27, "onCourt": false, "fullMinute": false, "onCourtSeconds": 0.0, "plusMinus": 0, "pts": 0, "stats": {"pts": 0, "reb": 0, "ast": 0, "stl": 0, "blk": 0, "fgm": 0, "fga": 0, "fg3m": 0, "fg3a": 0, "ftm": 0, "fta": 0, "pf": 0, "tov": 0}}, {"minute": 28, "onCourt": false, "fullMinute": false, "onCourtSeconds": 0.0, "plusMinus": 0, "pts": 0, "stats": {"pts": 0, "reb": 0, "ast": 0, "stl": 0, "blk": 0, "fgm": 0, "fga": 0, "fg3m": 0, "fg3a": 0, "ftm": 0, "fta": 0, "pf": 0, "tov": 0}}, {"minute": 29, "onCourt": true, "fullMinute": false, "onCourtSeconds": 39.0, "plusMinus": 5, "pts": 0, "stats": {"pts": 0, "reb": 0, "ast": 0, "stl": 0, "blk": 0, "fgm": 0, "fga": 0, "fg3m": 0, "fg3a": 0, "ftm": 0, "fta": 0, "pf": 0, "tov": 0}}, {"minute": 30, "onCourt": true, "fullMinute": true, "onCourtSeconds": 60.0, "plusMinus": -2, "pts": 3, "stats": {"pts": 3, "reb": 0, "ast": 0, "stl": 0, "blk": 0, "fgm": 1, "fga": 1, "fg3m": 1, "fg3a": 1, "ftm": 0, "fta": 0, "pf": 0, "tov": 0}}, {"minute": 31, "onCourt": true, "fullMinute": true, "onCourtSeconds": 60.0, "plusMinus": -2, "pts": 0, "stats": {"pts": 0, "reb": 0, "ast": 0, "stl": 0, "blk": 0, "fgm": 0, "fga": 0, "fg3m": 0, "fg3a": 0, "ftm": 0, "fta": 0, "pf": 0, "tov": 0}}, {"minute": 32, "onCourt": true, "fullMinute": true, "onCourtSeconds": 60.0, "plusMinus": 2, "pts": 0, "stats": {"pts": 0, "reb": 0, "ast": 0, "stl": 0, "blk": 0, "fgm": 0, "fga": 0, "fg3m": 0, "fg3a": 0, "ftm": 0, "fta": 0, "pf": 0, "tov": 0}}, {"minute": 33, "onCourt": true, "fullMinute": false, "onCourtSeconds": 30.0, "plusMinus": -2, "pts": 0, "stats": {"pts": 0, "reb": 0, "ast": 0, "stl": 0, "blk": 0, "fgm": 0, "fga": 1, "fg3m": 0, "fg3a": 0, "ftm": 0, "fta": 0, "pf": 0, "tov": 0}}, {"minute": 34, "onCourt": false, "fullMinute": false, "onCourtSeconds": 0.0, "plusMinus": 0, "pts": 0, "stats": {"pts": 0, "reb": 0, "ast": 0, "stl": 0, "blk": 0, "fgm": 0, "fga": 0, "fg3m": 0, "fg3a": 0, "ftm": 0, "fta": 0, "pf": 0, "tov": 0}}, {"minute": 35, "onCourt": false, "fullMinute": false, "onCourtSeconds": 0.0, "plusMinus": 0, "pts": 0, "stats": {"pts": 0, "reb": 0, "ast": 0, "stl": 0, "blk": 0, "fgm": 0, "fga": 0, "fg3m": 0, "fg3a": 0, "ftm": 0, "fta": 0, "pf": 0, "tov": 0}}, {"minute": 36, "onCourt": false, "fullMinute": false, "onCourtSeconds": 0.0, "plusMinus": 0, "pts": 0, "stats": {"pts": 0, "reb": 0, "ast": 0, "stl": 0, "blk": 0, "fgm": 0, "fga": 0, "fg3m": 0, "fg3a": 0, "ftm": 0, "fta": 0, "pf": 0, "tov": 0}}, {"minute": 37, "onCourt": false, "fullMinute": false, "onCourtSeconds": 0.0, "plusMinus": 0, "pts": 0, "stats": {"pts": 0, "reb": 0, "ast": 0, "stl": 0, "blk": 0, "fgm": 0, "fga": 0, "fg3m": 0, "fg3a": 0, "ftm": 0, "fta": 0, "pf": 0, "tov": 0}}, {"minute": 38, "onCourt": true, "fullMinute": false, "onCourtSeconds": 47.0, "plusMinus": -1, "pts": 0, "stats": {"pts": 0, "reb": 0, "ast": 0, "stl": 0, "blk": 0, "fgm": 0, "fga": 0, "fg3m": 0, "fg3a": 0, "ftm": 0, "fta": 0, "pf": 0, "tov": 0}}, {"minute": 39, "onCourt": true, "fullMinute": true, "onCourtSeconds": 60.0, "plusMinus": 2, "pts": 3, "stats": {"pts": 3, "reb": 0, "ast": 1, "stl": 1, "blk": 0, "fgm": 1, "fga": 1, "fg3m": 1, "fg3a": 1, "ftm": 0, "fta": 0, "pf": 0, "tov": 0}}], "gameStats": {"pts": 6, "reb": 0, "ast": 1, "stl": 1, "blk": 0, "fgm": 2, "fga": 3, "fg3m": 2, "fg3a": 2, "ftm": 0, "fta": 0, "pf": 0, "tov": 0}, "totalPlusMinus": 2}, {"gameId": "2791977", "date": "2026-01-10", "teamCode": "SKS", "teamName": "SK Slavia Praha", "opponent": "USK Praha", "isHome": true, "score": "86:71", "numOT": 0, "isDNP": false, "totalSeconds": 464, "periods": [{"period": 1, "label": "Q1", "startMinute": 0, "endMinute": 10, "duration": 10}, {"period": 2, "label": "Q2", "startMinute": 10, "endMinute": 20, "duration": 10}, {"period": 3, "label": "Q3", "startMinute": 20, "endMinute": 30, "duration": 10}, {"period": 4, "label": "Q4", "startMinute": 30, "endMinute": 40, "duration": 10}], "minutes": [{"minute": 0, "onCourt": false, "fullMinute": false, "onCourtSeconds": 0.0, "plusMinus": 0, "pts": 0, "stats": {"pts": 0, "reb": 0, "ast": 0, "stl": 0, "blk": 0, "fgm": 0, "fga": 0, "fg3m": 0, "fg3a": 0, "ftm": 0, "fta": 0, "pf": 0, "tov": 0}}, {"minute": 1, "onCourt": false, "fullMinute": false, "onCourtSeconds": 0.0, "plusMinus": 0, "pts": 0, "stats": {"pts": 0, "reb": 0, "ast": 0, "stl": 0, "blk": 0, "fgm": 0, "fga": 0, "fg3m": 0, "fg3a": 0, "ftm": 0, "fta": 0, "pf": 0, "tov": 0}}, {"minute": 2, "onCourt": false, "fullMinute": false, "onCourtSeconds": 0.0, "plusMinus": 0, "pts": 0, "stats": {"pts": 0, "reb": 0, "ast": 0, "stl": 0, "blk": 0, "fgm": 0, "fga": 0, "fg3m": 0, "fg3a": 0, "ftm": 0, "fta": 0, "pf": 0, "tov": 0}}, {"minute": 3, "onCourt": false, "fullMinute": false, "onCourtSeconds": 0.0, "plusMinus": 0, "pts": 0, "stats": {"pts": 0, "reb": 0, "ast": 0, "stl": 0, "blk": 0, "fgm": 0, "fga": 0, "fg3m": 0, "fg3a": 0, "ftm": 0, "fta": 0, "pf": 0, "tov": 0}}, {"minute": 4, "onCourt": false, "fullMinute": false, "onCourtSeconds": 0.0, "plusMinus": 0, "pts": 0, "stats": {"pts": 0, "reb": 0, "ast": 0, "stl": 0, "blk": 0, "fgm": 0, "fga": 0, "fg3m": 0, "fg3a": 0, "ftm": 0, "fta": 0, "pf": 0, "tov": 0}}, {"minute": 5, "onCourt": false, "fullMinute": false, "onCourtSeconds": 0.0, "plusMinus": 0, "pts": 0, "stats": {"pts": 0, "reb": 0, "ast": 0, "stl": 0, "blk": 0, "fgm": 0, "fga": 0, "fg3m": 0, "fg3a": 0, "ftm": 0, "fta": 0, "pf": 0, "tov": 0}}, {"minute": 6, "onCourt": false, "fullMinute": false, "onCourtSeconds": 0.0, "plusMinus": 0, "pts": 0, "stats": {"pts": 0, "reb": 0, "ast": 0, "stl": 0, "blk": 0, "fgm": 0, "fga": 0, "fg3m": 0, "fg3a": 0, "ftm": 0, "fta": 0, "pf": 0, "tov": 0}}, {"minute": 7, "onCourt": true, "fullMinute": false, "onCourtSeconds": 22.0, "plusMinus": 2, "pts": 0, "stats": {"pts": 0, "reb": 0, "ast": 0, "stl": 0, "blk": 0, "fgm": 0, "fga": 0, "fg3m": 0, "fg3a": 0, "ftm": 0, "fta": 0, "pf": 0, "tov": 0}}, {"minute": 8, "onCourt": true, "fullMinute": true, "onCourtSeconds": 60.0, "plusMinus": -3, "pts": 0, "stats": {"pts": 0, "reb": 0, "ast": 0, "stl": 0, "blk": 0, "fgm": 0, "fga": 0, "fg3m": 0, "fg3a": 0, "ftm": 0, "fta": 0, "pf": 0, "tov": 0}}, {"minute": 9, "onCourt": true, "fullMinute": true, "onCourtSeconds": 60.0, "plusMinus": 2, "pts": 0, "stats": {"pts": 0, "reb": 0, "ast": 0, "stl": 0, "blk": 0, "fgm": 0, "fga": 0, "fg3m": 0, "fg3a": 0, "ftm": 0, "fta": 0, "pf": 0, "tov": 0}}, {"minute": 10, "onCourt": true, "fullMinute": true, "onCourtSeconds": 60.0, "plusMinus": 3, "pts": 0, "stats": {"pts": 0, "reb": 0, "ast": 0, "stl": 0, "blk": 0, "fgm": 0, "fga": 0, "fg3m": 0, "fg3a": 0, "ftm": 0, "fta": 0, "pf": 0, "tov": 0}}, {"minute": 11, "onCourt": true, "fullMinute": true, "onCourtSeconds": 60.0, "plusMinus": 6, "pts": 0, "stats": {"pts": 0, "reb": 0, "ast": 2, "stl": 1, "blk": 0, "fgm": 0, "fga": 1, "fg3m": 0, "fg3a": 1, "ftm": 0, "fta": 0, "pf": 0, "tov": 0}}, {"minute": 12, "onCourt": true, "fullMinute": false, "onCourtSeconds": 20.0, "plusMinus": 0, "pts": 0, "stats": {"pts": 0, "reb": 0, "ast": 0, "stl": 0, "blk": 0, "fgm": 0, "fga": 0, "fg3m": 0, "fg3a": 0, "ftm": 0, "fta": 0, "pf": 1, "tov": 0}}, {"minute": 13, "onCourt": false, "fullMinute": false, "onCourtSeconds": 0.0, "plusMinus": 0, "pts": 0, "stats": {"pts": 0, "reb": 0, "ast": 0, "stl": 0, "blk": 0, "fgm": 0, "fga": 0, "fg3m": 0, "fg3a": 0, "ftm": 0, "fta": 0, "pf": 0, "tov": 0}}, {"minute": 14, "onCourt": false, "fullMinute": false, "onCourtSeconds": 0.0, "plusMinus": 0, "pts": 0, "stats": {"pts": 0, "reb": 0, "ast": 0, "stl": 0, "blk": 0, "fgm": 0, "fga": 0, "fg3m": 0, "fg3a": 0, "ftm": 0, "fta": 0, "pf": 0, "tov": 0}}, {"minute": 15, "onCourt": false, "fullMinute": false, "onCourtSeconds": 0.0, "plusMinus": 0, "pts": 0, "stats": {"pts": 0, "reb": 0, "ast": 0, "stl": 0, "blk": 0, "fgm": 0, "fga": 0, "fg3m": 0, "fg3a": 0, "ftm": 0, "fta": 0, "pf": 0, "tov": 0}}, {"minute": 16, "onCourt": false, "fullMinute": false, "onCourtSeconds": 0.0, "plusMinus": 0, "pts": 0, "stats": {"pts": 0, "reb": 0, "ast": 0, "stl": 0, "blk": 0, "fgm": 0, "fga": 0, "fg3m": 0, "fg3a": 0, "ftm": 0, "fta": 0, "pf": 0, "tov": 0}}, {"minute": 17, "onCourt": true, "fullMinute": false, "onCourtSeconds": 9.0, "plusMinus": 1, "pts": 0, "stats": {"pts": 0, "reb": 0, "ast": 0, "stl": 0, "blk": 0, "fgm": 0, "fga": 0, "fg3m": 0, "fg3a": 0, "ftm": 0, "fta": 0, "pf": 0, "tov": 0}}, {"minute": 18, "onCourt": false, "fullMinute": false, "onCourtSeconds": 0.0, "plusMinus": 0, "pts": 0, "stats": {"pts": 0, "reb": 0, "ast": 0, "stl": 0, "blk": 0, "fgm": 0, "fga": 0, "fg3m": 0, "fg3a": 0, "ftm": 0, "fta": 0, "pf": 0, "tov": 0}}, {"minute": 19, "onCourt": false, "fullMinute": false, "onCourtSeconds": 0.0, "plusMinus": 0, "pts": 0, "stats": {"pts": 0, "reb": 0, "ast": 0, "stl": 0, "blk": 0, "fgm": 0, "fga": 0, "fg3m": 0, "fg3a": 0, "ftm": 0, "fta": 0, "pf": 0, "tov": 0}}, {"minute": 20, "onCourt": true, "fullMinute": true, "onCourtSeconds": 60.0, "plusMinus": -2, "pts": 0, "stats": {"pts": 0, "reb": 0, "ast": 0, "stl": 0, "blk": 0, "fgm": 0, "fga": 0, "fg3m": 0, "fg3a": 0, "ftm": 0, "fta": 0, "pf": 0, "tov": 1}}, {"minute": 21, "onCourt": true, "fullMinute": true, "onCourtSeconds": 60.0, "plusMinus": -1, "pts": 0, "stats": {"pts": 0, "reb": 0, "ast": 0, "stl": 0, "blk": 0, "fgm": 0, "fga": 0, "fg3m": 0, "fg3a": 0, "ftm": 0, "fta": 0, "pf": 1, "tov": 0}}, {"minute": 22, "onCourt": true, "fullMinute": false, "onCourtSeconds": 36.0, "plusMinus": -3, "pts": 0, "stats": {"pts": 0, "reb": 0, "ast": 0, "stl": 0, "blk": 0, "fgm": 0, "fga": 0, "fg3m": 0, "fg3a": 0, "ftm": 0, "fta": 0, "pf": 0, "tov": 0}}, {"minute": 23, "onCourt": false, "fullMinute": false, "onCourtSeconds": 0.0, "plusMinus": 0, "pts": 0, "stats": {"pts": 0, "reb": 0, "ast": 0, "stl": 0, "blk": 0, "fgm": 0, "fga": 0, "fg3m": 0, "fg3a": 0, "ftm": 0, "fta": 0, "pf": 0, "tov": 0}}, {"minute": 24, "onCourt": false, "fullMinute": false, "onCourtSeconds": 0.0, "plusMinus": 0, "pts": 0, "stats": {"pts": 0, "reb": 0, "ast": 0, "stl": 0, "blk": 0, "fgm": 0, "fga": 0, "fg3m": 0, "fg3a": 0, "ftm": 0, "fta": 0, "pf": 0, "tov": 0}}, {"minute": 25, "onCourt": false, "fullMinute": false, "onCourtSeconds": 0.0, "plusMinus": 0, "pts": 0, "stats": {"pts": 0, "reb": 0, "ast": 0, "stl": 0, "blk": 0, "fgm": 0, "fga": 0, "fg3m": 0, "fg3a": 0, "ftm": 0, "fta": 0, "pf": 0, "tov": 0}}, {"minute": 26, "onCourt": false, "fullMinute": false, "onCourtSeconds": 0.0, "plusMinus": 0, "pts": 0, "stats": {"pts": 0, "reb": 0, "ast": 0, "stl": 0, "blk": 0, "fgm": 0, "fga": 0, "fg3m": 0, "fg3a": 0, "ftm": 0, "fta": 0, "pf": 0, "tov": 0}}, {"minute": 27, "onCourt": false, "fullMinute": false, "onCourtSeconds": 0.0, "plusMinus": 0, "pts": 0, "stats": {"pts": 0, "reb": 0, "ast": 0, "stl": 0, "blk": 0, "fgm": 0, "fga": 0, "fg3m": 0, "fg3a": 0, "ftm": 0, "fta": 0, "pf": 0, "tov": 0}}, {"minute": 28, "onCourt": true, "fullMinute": false, "onCourtSeconds": 11.0, "plusMinus": 0, "pts": 0, "stats": {"pts": 0, "reb": 0, "ast": 0, "stl": 0, "blk": 0, "fgm": 0, "fga": 0, "fg3m": 0, "fg3a": 0, "ftm": 0, "fta": 0, "pf": 0, "tov": 0}}, {"minute": 29, "onCourt": true, "fullMinute": false, "onCourtSeconds": 6.0, "plusMinus": 1, "pts": 0, "stats": {"pts": 0, "reb": 0, "ast": 0, "stl": 0, "blk": 0, "fgm": 0, "fga": 0, "fg3m": 0, "fg3a": 0, "ftm": 0, "fta": 0, "pf": 0, "tov": 0}}, {"minute": 30, "onCourt": false, "fullMinute": false, "onCourtSeconds": 0.0, "plusMinus": 0, "pts": 0, "stats": {"pts": 0, "reb": 0, "ast": 0, "stl": 0, "blk": 0, "fgm": 0, "fga": 0, "fg3m": 0, "fg3a": 0, "ftm": 0, "fta": 0, "pf": 0, "tov": 0}}, {"minute": 31, "onCourt": false, "fullMinute": false, "onCourtSeconds": 0.0, "plusMinus": 0, "pts": 0, "stats": {"pts": 0, "reb": 0, "ast": 0, "stl": 0, "blk": 0, "fgm": 0, "fga": 0, "fg3m": 0, "fg3a": 0, "ftm": 0, "fta": 0, "pf": 0, "tov": 0}}, {"minute": 32, "onCourt": false, "fullMinute": false, "onCourtSeconds": 0.0, "plusMinus": 0, "pts": 0, "stats": {"pts": 0, "reb": 0, "ast": 0, "stl": 0, "blk": 0, "fgm": 0, "fga": 0, "fg3m": 0, "fg3a": 0, "ftm": 0, "fta": 0, "pf": 0, "tov": 0}}, {"minute": 33, "onCourt": false, "fullMinute": false, "onCourtSeconds": 0.0, "plusMinus": 0, "pts": 0, "stats": {"pts": 0, "reb": 0, "ast": 0, "stl": 0, "blk": 0, "fgm": 0, "fga": 0, "fg3m": 0, "fg3a": 0, "ftm": 0, "fta": 0, "pf": 0, "tov": 0}}, {"minute": 34, "onCourt": false, "fullMinute": false, "onCourtSeconds": 0.0, "plusMinus": 0, "pts": 0, "stats": {"pts": 0, "reb": 0, "ast": 0, "stl": 0, "blk": 0, "fgm": 0, "fga": 0, "fg3m": 0, "fg3a": 0, "ftm": 0, "fta": 0, "pf": 0, "tov": 0}}, {"minute": 35, "onCourt": false, "fullMinute": false, "onCourtSeconds": 0.0, "plusMinus": 0, "pts": 0, "stats": {"pts": 0, "reb": 0, "ast": 0, "stl": 0, "blk": 0, "fgm": 0, "fga": 0, "fg3m": 0, "fg3a": 0, "ftm": 0, "fta": 0, "pf": 0, "tov": 0}}, {"minute": 36, "onCourt": false, "fullMinute": false, "onCourtSeconds": 0.0, "plusMinus": 0, "pts": 0, "stats": {"pts": 0, "reb": 0, "ast": 0, "stl": 0, "blk": 0, "fgm": 0, "fga": 0, "fg3m": 0, "fg3a": 0, "ftm": 0, "fta": 0, "pf": 0, "tov": 0}}, {"minute": 37, "onCourt": false, "fullMinute": false, "onCourtSeconds": 0.0, "plusMinus": 0, "pts": 0, "stats": {"pts": 0, "reb": 0, "ast": 0, "stl": 0, "blk": 0, "fgm": 0, "fga": 0, "fg3m": 0, "fg3a": 0, "ftm": 0, "fta": 0, "pf": 0, "tov": 0}}, {"minute": 38, "onCourt": false, "fullMinute": false, "onCourtSeconds": 0.0, "plusMinus": 0, "pts": 0, "stats": {"pts": 0, "reb": 0, "ast": 0, "stl": 0, "blk": 0, "fgm": 0, "fga": 0, "fg3m": 0, "fg3a": 0, "ftm": 0, "fta": 0, "pf": 0, "tov": 0}}, {"minute": 39, "onCourt": false, "fullMinute": false, "onCourtSeconds": 0.0, "plusMinus": 0, "pts": 0, "stats": {"pts": 0, "reb": 0, "ast": 0, "stl": 0, "blk": 0, "fgm": 0, "fga": 0, "fg3m": 0, "fg3a": 0, "ftm": 0, "fta": 0, "pf": 0, "tov": 0}}], "gameStats": {"pts": 0, "reb": 0, "ast": 2, "stl": 1, "blk": 0, "fgm": 0, "fga": 1, "fg3m": 0, "fg3a": 1, "ftm": 0, "fta": 0, "pf": 3, "tov": 1}, "totalPlusMinus": 6}, {"gameId": "2794571", "date": "2026-01-17", "teamCode": "SKS", "teamName": "SK Slavia Praha", "opponent": "NH Ostrava", "isHome": true, "score": "74:77", "numOT": 0, "isDNP": true, "totalSeconds": 0, "periods": [{"period": 1, "label": "Q1", "startMinute": 0, "endMinute": 10, "duration": 10}, {"period": 2, "label": "Q2", "startMinute": 10, "endMinute": 20, "duration": 10}, {"period": 3, "label": "Q3", "startMinute": 20, "endMinute": 30, "duration": 10}, {"period": 4, "label": "Q4", "startMinute": 30, "endMinute": 40, "duration": 10}], "minutes": [], "gameStats": {"pts": 0, "reb": 0, "ast": 0, "stl": 0, "blk": 0, "fgm": 0, "fga": 0, "fg3m": 0, "fg3a": 0, "ftm": 0, "fta": 0, "pf": 0, "tov": 0}, "totalPlusMinus": 0}, {"gameId": "2803574", "date": "2026-01-24", "teamCode": "SKS", "teamName": "SK Slavia Praha", "opponent": "BK Olomoucko", "isHome": false, "score": "84:97", "numOT": 0, "isDNP": false, "totalSeconds": 437, "periods": [{"period": 1, "label": "Q1", "startMinute": 0, "endMinute": 10, "duration": 10}, {"period": 2, "label": "Q2", "startMinute": 10, "endMinute": 20, "duration": 10}, {"period": 3, "label": "Q3", "startMinute": 20, "endMinute": 30, "duration": 10}, {"period": 4, "label": "Q4", "startMinute": 30, "endMinute": 40, "duration": 10}], "minutes": [{"minute": 0, "onCourt": false, "fullMinute": false, "onCourtSeconds": 0.0, "plusMinus": 0, "pts": 0, "stats": {"pts": 0, "reb": 0, "ast": 0, "stl": 0, "blk": 0, "fgm": 0, "fga": 0, "fg3m": 0, "fg3a": 0, "ftm": 0, "fta": 0, "pf": 0, "tov": 0}}, {"minute": 1, "onCourt": false, "fullMinute": false, "onCourtSeconds": 0.0, "plusMinus": 0, "pts": 0, "stats": {"pts": 0, "reb": 0, "ast": 0, "stl": 0, "blk": 0, "fgm": 0, "fga": 0, "fg3m": 0, "fg3a": 0, "ftm": 0, "fta": 0, "pf": 0, "tov": 0}}, {"minute": 2, "onCourt": false, "fullMinute": false, "onCourtSeconds": 0.0, "plusMinus": 0, "pts": 0, "stats": {"pts": 0, "reb": 0, "ast": 0, "stl": 0, "blk": 0, "fgm": 0, "fga": 0, "fg3m": 0, "fg3a": 0, "ftm": 0, "fta": 0, "pf": 0, "tov": 0}}, {"minute": 3, "onCourt": false, "fullMinute": false, "onCourtSeconds": 0.0, "plusMinus": 0, "pts": 0, "stats": {"pts": 0, "reb": 0, "ast": 0, "stl": 0, "blk": 0, "fgm": 0, "fga": 0, "fg3m": 0, "fg3a": 0, "ftm": 0, "fta": 0, "pf": 0, "tov": 0}}, {"minute": 4, "onCourt": false, "fullMinute": false, "onCourtSeconds": 0.0, "plusMinus": 0, "pts": 0, "stats": {"pts": 0, "reb": 0, "ast": 0, "stl": 0, "blk": 0, "fgm": 0, "fga": 0, "fg3m": 0, "fg3a": 0, "ftm": 0, "fta": 0, "pf": 0, "tov": 0}}, {"minute": 5, "onCourt": false, "fullMinute": false, "onCourtSeconds": 0.0, "plusMinus": 0, "pts": 0, "stats": {"pts": 0, "reb": 0, "ast": 0, "stl": 0, "blk": 0, "fgm": 0, "fga": 0, "fg3m": 0, "fg3a": 0, "ftm": 0, "fta": 0, "pf": 0, "tov": 0}}, {"minute": 6, "onCourt": false, "fullMinute": false, "onCourtSeconds": 0.0, "plusMinus": 0, "pts": 0, "stats": {"pts": 0, "reb": 0, "ast": 0, "stl": 0, "blk": 0, "fgm": 0, "fga": 0, "fg3m": 0, "fg3a": 0, "ftm": 0, "fta": 0, "pf": 0, "tov": 0}}, {"minute": 7, "onCourt": true, "fullMinute": false, "onCourtSeconds": 46.0, "plusMinus": -4, "pts": 0, "stats": {"pts": 0, "reb": 1, "ast": 0, "stl": 0, "blk": 0, "fgm": 0, "fga": 0, "fg3m": 0, "fg3a": 0, "ftm": 0, "fta": 0, "pf": 1, "tov": 0}}, {"minute": 8, "onCourt": true, "fullMinute": true, "onCourtSeconds": 60.0, "plusMinus": 0, "pts": 0, "stats": {"pts": 0, "reb": 0, "ast": 0, "stl": 0, "blk": 0, "fgm": 0, "fga": 0, "fg3m": 0, "fg3a": 0, "ftm": 0, "fta": 0, "pf": 0, "tov": 0}}, {"minute": 9, "onCourt": true, "fullMinute": true, "onCourtSeconds": 60.0, "plusMinus": 3, "pts": 0, "stats": {"pts": 0, "reb": 0, "ast": 0, "stl": 0, "blk": 0, "fgm": 0, "fga": 0, "fg3m": 0, "fg3a": 0, "ftm": 0, "fta": 0, "pf": 0, "tov": 0}}, {"minute": 10, "onCourt": false, "fullMinute": false, "onCourtSeconds": 0.0, "plusMinus": 0, "pts": 0, "stats": {"pts": 0, "reb": 0, "ast": 0, "stl": 0, "blk": 0, "fgm": 0, "fga": 0, "fg3m": 0, "fg3a": 0, "ftm": 0, "fta": 0, "pf": 0, "tov": 0}}, {"minute": 11, "onCourt": false, "fullMinute": false, "onCourtSeconds": 0.0, "plusMinus": 0, "pts": 0, "stats": {"pts": 0, "reb": 0, "ast": 0, "stl": 0, "blk": 0, "fgm": 0, "fga": 0, "fg3m": 0, "fg3a": 0, "ftm": 0, "fta": 0, "pf": 0, "tov": 0}}, {"minute": 12, "onCourt": false, "fullMinute": false, "onCourtSeconds": 0.0, "plusMinus": 0, "pts": 0, "stats": {"pts": 0, "reb": 0, "ast": 0, "stl": 0, "blk": 0, "fgm": 0, "fga": 0, "fg3m": 0, "fg3a": 0, "ftm": 0, "fta": 0, "pf": 0, "tov": 0}}, {"minute": 13, "onCourt": false, "fullMinute": false, "onCourtSeconds": 0.0, "plusMinus": 0, "pts": 0, "stats": {"pts": 0, "reb": 0, "ast": 0, "stl": 0, "blk": 0, "fgm": 0, "fga": 0, "fg3m": 0, "fg3a": 0, "ftm": 0, "fta": 0, "pf": 0, "tov": 0}}, {"minute": 14, "onCourt": false, "fullMinute": false, "onCourtSeconds": 0.0, "plusMinus": 0, "pts": 0, "stats": {"pts": 0, "reb": 0, "ast": 0, "stl": 0, "blk": 0, "fgm": 0, "fga": 0, "fg3m": 0, "fg3a": 0, "ftm": 0, "fta": 0, "pf": 0, "tov": 0}}, {"minute": 15, "onCourt": false, "fullMinute": false, "onCourtSeconds": 0.0, "plusMinus": 0, "pts": 0, "stats": {"pts": 0, "reb": 0, "ast": 0, "stl": 0, "blk": 0, "fgm": 0, "fga": 0, "fg3m": 0, "fg3a": 0, "ftm": 0, "fta": 0, "pf": 0, "tov": 0}}, {"minute": 16, "onCourt": true, "fullMinute": false, "onCourtSeconds": 29.0, "plusMinus": 0, "pts": 0, "stats": {"pts": 0, "reb": 0, "ast": 1, "stl": 0, "blk": 0, "fgm": 0, "fga": 0, "fg3m": 0, "fg3a": 0, "ftm": 0, "fta": 0, "pf": 0, "tov": 0}}, {"minute": 17, "onCourt": true, "fullMinute": true, "onCourtSeconds": 60.0, "plusMinus": -5, "pts": 0, "stats": {"pts": 0, "reb": 0, "ast": 0, "stl": 0, "blk": 0, "fgm": 0, "fga": 0, "fg3m": 0, "fg3a": 0, "ftm": 0, "fta": 0, "pf": 0, "tov": 0}}, {"minute": 18, "onCourt": true, "fullMinute": false, "onCourtSeconds": 45.0, "plusMinus": 1, "pts": 0, "stats": {"pts": 0, "reb": 0, "ast": 0, "stl": 0, "blk": 0, "fgm": 0, "fga": 0, "fg3m": 0, "fg3a": 0, "ftm": 0, "fta": 0, "pf": 0, "tov": 0}}, {"minute": 19, "onCourt": false, "fullMinute": false, "onCourtSeconds": 0.0, "plusMinus": 0, "pts": 0, "stats": {"pts": 0, "reb": 0, "ast": 0, "stl": 0, "blk": 0, "fgm": 0, "fga": 0, "fg3m": 0, "fg3a": 0, "ftm": 0, "fta": 0, "pf": 0, "tov": 0}}, {"minute": 20, "onCourt": false, "fullMinute": false, "onCourtSeconds": 0.0, "plusMinus": 0, "pts": 0, "stats": {"pts": 0, "reb": 0, "ast": 0, "stl": 0, "blk": 0, "fgm": 0, "fga": 0, "fg3m": 0, "fg3a": 0, "ftm": 0, "fta": 0, "pf": 0, "tov": 0}}, {"minute": 21, "onCourt": false, "fullMinute": false, "onCourtSeconds": 0.0, "plusMinus": 0, "pts": 0, "stats": {"pts": 0, "reb": 0, "ast": 0, "stl": 0, "blk": 0, "fgm": 0, "fga": 0, "fg3m": 0, "fg3a": 0, "ftm": 0, "fta": 0, "pf": 0, "tov": 0}}, {"minute": 22, "onCourt": false, "fullMinute": false, "onCourtSeconds": 0.0, "plusMinus": 0, "pts": 0, "stats": {"pts": 0, "reb": 0, "ast": 0, "stl": 0, "blk": 0, "fgm": 0, "fga": 0, "fg3m": 0, "fg3a": 0, "ftm": 0, "fta": 0, "pf": 0, "tov": 0}}, {"minute": 23, "onCourt": false, "fullMinute": false, "onCourtSeconds": 0.0, "plusMinus": 0, "pts": 0, "stats": {"pts": 0, "reb": 0, "ast": 0, "stl": 0, "blk": 0, "fgm": 0, "fga": 0, "fg3m": 0, "fg3a": 0, "ftm": 0, "fta": 0, "pf": 0, "tov": 0}}, {"minute": 24, "onCourt": false, "fullMinute": false, "onCourtSeconds": 0.0, "plusMinus": 0, "pts": 0, "stats": {"pts": 0, "reb": 0, "ast": 0, "stl": 0, "blk": 0, "fgm": 0, "fga": 0, "fg3m": 0, "fg3a": 0, "ftm": 0, "fta": 0, "pf": 0, "tov": 0}}, {"minute": 25, "onCourt": false, "fullMinute": false, "onCourtSeconds": 0.0, "plusMinus": 0, "pts": 0, "stats": {"pts": 0, "reb": 0, "ast": 0, "stl": 0, "blk": 0, "fgm": 0, "fga": 0, "fg3m": 0, "fg3a": 0, "ftm": 0, "fta": 0, "pf": 0, "tov": 0}}, {"minute": 26, "onCourt": true, "fullMinute": false, "onCourtSeconds": 9.0, "plusMinus": 2, "pts": 0, "stats": {"pts": 0, "reb": 0, "ast": 0, "stl": 0, "blk": 0, "fgm": 0, "fga": 0, "fg3m": 0, "fg3a": 0, "ftm": 0, "fta": 0, "pf": 0, "tov": 0}}, {"minute": 27, "onCourt": true, "fullMinute": true, "onCourtSeconds": 60.0, "plusMinus": -4, "pts": 0, "stats": {"pts": 0, "reb": 0, "ast": 0, "stl": 0, "blk": 0, "fgm": 0, "fga": 0, "fg3m": 0, "fg3a": 0, "ftm": 0, "fta": 0, "pf": 2, "tov": 0}}, {"minute": 28, "onCourt": true, "fullMinute": true, "onCourtSeconds": 60.0, "plusMinus": 0, "pts": 0, "stats": {"pts": 0, "reb": 0, "ast": 1, "stl": 0, "blk": 0, "fgm": 0, "fga": 0, "fg3m": 0, "fg3a": 0, "ftm": 0, "fta": 0, "pf": 0, "tov": 0}}, {"minute": 29, "onCourt": true, "fullMinute": false, "onCourtSeconds": 8.0, "plusMinus": 0, "pts": 0, "stats": {"pts": 0, "reb": 0, "ast": 0, "stl": 0, "blk": 0, "fgm": 0, "fga": 0, "fg3m": 0, "fg3a": 0, "ftm": 0, "fta": 0, "pf": 0, "tov": 0}}, {"minute": 30, "onCourt": false, "fullMinute": false, "onCourtSeconds": 0.0, "plusMinus": 0, "pts": 0, "stats": {"pts": 0, "reb": 0, "ast": 0, "stl": 0, "blk": 0, "fgm": 0, "fga": 0, "fg3m": 0, "fg3a": 0, "ftm": 0, "fta": 0, "pf": 0, "tov": 0}}, {"minute": 31, "onCourt": false, "fullMinute": false, "onCourtSeconds": 0.0, "plusMinus": 0, "pts": 0, "stats": {"pts": 0, "reb": 0, "ast": 0, "stl": 0, "blk": 0, "fgm": 0, "fga": 0, "fg3m": 0, "fg3a": 0, "ftm": 0, "fta": 0, "pf": 0, "tov": 0}}, {"minute": 32, "onCourt": false, "fullMinute": false, "onCourtSeconds": 0.0, "plusMinus": 0, "pts": 0, "stats": {"pts": 0, "reb": 0, "ast": 0, "stl": 0, "blk": 0, "fgm": 0, "fga": 0, "fg3m": 0, "fg3a": 0, "ftm": 0, "fta": 0, "pf": 0, "tov": 0}}, {"minute": 33, "onCourt": false, "fullMinute": false, "onCourtSeconds": 0.0, "plusMinus": 0, "pts": 0, "stats": {"pts": 0, "reb": 0, "ast": 0, "stl": 0, "blk": 0, "fgm": 0, "fga": 0, "fg3m": 0, "fg3a": 0, "ftm": 0, "fta": 0, "pf": 0, "tov": 0}}, {"minute": 34, "onCourt": false, "fullMinute": false, "onCourtSeconds": 0.0, "plusMinus": 0, "pts": 0, "stats": {"pts": 0, "reb": 0, "ast": 0, "stl": 0, "blk": 0, "fgm": 0, "fga": 0, "fg3m": 0, "fg3a": 0, "ftm": 0, "fta": 0, "pf": 0, "tov": 0}}, {"minute": 35, "onCourt": false, "fullMinute": false, "onCourtSeconds": 0.0, "plusMinus": 0, "pts": 0, "stats": {"pts": 0, "reb": 0, "ast": 0, "stl": 0, "blk": 0, "fgm": 0, "fga": 0, "fg3m": 0, "fg3a": 0, "ftm": 0, "fta": 0, "pf": 0, "tov": 0}}, {"minute": 36, "onCourt": false, "fullMinute": false, "onCourtSeconds": 0.0, "plusMinus": 0, "pts": 0, "stats": {"pts": 0, "reb": 0, "ast": 0, "stl": 0, "blk": 0, "fgm": 0, "fga": 0, "fg3m": 0, "fg3a": 0, "ftm": 0, "fta": 0, "pf": 0, "tov": 0}}, {"minute": 37, "onCourt": false, "fullMinute": false, "onCourtSeconds": 0.0, "plusMinus": 0, "pts": 0, "stats": {"pts": 0, "reb": 0, "ast": 0, "stl": 0, "blk": 0, "fgm": 0, "fga": 0, "fg3m": 0, "fg3a": 0, "ftm": 0, "fta": 0, "pf": 0, "tov": 0}}, {"minute": 38, "onCourt": false, "fullMinute": false, "onCourtSeconds": 0.0, "plusMinus": 0, "pts": 0, "stats": {"pts": 0, "reb": 0, "ast": 0, "stl": 0, "blk": 0, "fgm": 0, "fga": 0, "fg3m": 0, "fg3a": 0, "ftm": 0, "fta": 0, "pf": 0, "tov": 0}}, {"minute": 39, "onCourt": false, "fullMinute": false, "onCourtSeconds": 0.0, "plusMinus": 0, "pts": 0, "stats": {"pts": 0, "reb": 0, "ast": 0, "stl": 0, "blk": 0, "fgm": 0, "fga": 0, "fg3m": 0, "fg3a": 0, "ftm": 0, "fta": 0, "pf": 0, "tov": 0}}], "gameStats": {"pts": 0, "reb": 1, "ast": 2, "stl": 0, "blk": 0, "fgm": 0, "fga": 0, "fg3m": 0, "fg3a": 0, "ftm": 0, "fta": 0, "pf": 3, "tov": 0}, "totalPlusMinus": -7}, {"gameId": "2803575", "date": "2026-01-31", "teamCode": "SKS", "teamName": "SK Slavia Praha", "opponent": "BK GAPA Hradec Kr\u00e1lov\u00e9", "isHome": false, "score": "76:73", "numOT": 0, "isDNP": true, "totalSeconds": 0, "periods": [{"period": 1, "label": "Q1", "startMinute": 0, "endMinute": 10, "duration": 10}, {"period": 2, "label": "Q2", "startMinute": 10, "endMinute": 20, "duration": 10}, {"period": 3, "label": "Q3", "startMinute": 20, "endMinute": 30, "duration": 10}, {"period": 4, "label": "Q4", "startMinute": 30, "endMinute": 40, "duration": 10}], "minutes": [], "gameStats": {"pts": 0, "reb": 0, "ast": 0, "stl": 0, "blk": 0, "fgm": 0, "fga": 0, "fg3m": 0, "fg3a": 0, "ftm": 0, "fta": 0, "pf": 0, "tov": 0}, "totalPlusMinus": 0}, {"gameId": "2803578", "date": "2026-02-07", "teamCode": "SKS", "teamName": "SK Slavia Praha", "opponent": "USK Praha", "isHome": true, "score": "98:94", "numOT": 0, "isDNP": true, "totalSeconds": 0, "periods": [{"period": 1, "label": "Q1", "startMinute": 0, "endMinute": 10, "duration": 10}, {"period": 2, "label": "Q2", "startMinute": 10, "endMinute": 20, "duration": 10}, {"period": 3, "label": "Q3", "startMinute": 20, "endMinute": 30, "duration": 10}, {"period": 4, "label": "Q4", "startMinute": 30, "endMinute": 40, "duration": 10}], "minutes": [], "gameStats": {"pts": 0, "reb": 0, "ast": 0, "stl": 0, "blk": 0, "fgm": 0, "fga": 0, "fg3m": 0, "fg3a": 0, "ftm": 0, "fta": 0, "pf": 0, "tov": 0}, "totalPlusMinus": 0}, {"gameId": "2805379", "date": "2026-02-15", "teamCode": "SKS", "teamName": "SK Slavia Praha", "opponent": "BK Olomoucko", "isHome": true, "score": "81:72", "numOT": 0, "isDNP": false, "totalSeconds": 16, "periods": [{"period": 1, "label": "Q1", "startMinute": 0, "endMinute": 10, "duration": 10}, {"period": 2, "label": "Q2", "startMinute": 10, "endMinute": 20, "duration": 10}, {"period": 3, "label": "Q3", "startMinute": 20, "endMinute": 30, "duration": 10}, {"period": 4, "label": "Q4", "startMinute": 30, "endMinute": 40, "duration": 10}], "minutes": [{"minute": 0, "onCourt": false, "fullMinute": false, "onCourtSeconds": 0.0, "plusMinus": 0, "pts": 0, "stats": {"pts": 0, "reb": 0, "ast": 0, "stl": 0, "blk": 0, "fgm": 0, "fga": 0, "fg3m": 0, "fg3a": 0, "ftm": 0, "fta": 0, "pf": 0, "tov": 0}}, {"minute": 1, "onCourt": false, "fullMinute": false, "onCourtSeconds": 0.0, "plusMinus": 0, "pts": 0, "stats": {"pts": 0, "reb": 0, "ast": 0, "stl": 0, "blk": 0, "fgm": 0, "fga": 0, "fg3m": 0, "fg3a": 0, "ftm": 0, "fta": 0, "pf": 0, "tov": 0}}, {"minute": 2, "onCourt": false, "fullMinute": false, "onCourtSeconds": 0.0, "plusMinus": 0, "pts": 0, "stats": {"pts": 0, "reb": 0, "ast": 0, "stl": 0, "blk": 0, "fgm": 0, "fga": 0, "fg3m": 0, "fg3a": 0, "ftm": 0, "fta": 0, "pf": 0, "tov": 0}}, {"minute": 3, "onCourt": false, "fullMinute": false, "onCourtSeconds": 0.0, "plusMinus": 0, "pts": 0, "stats": {"pts": 0, "reb": 0, "ast": 0, "stl": 0, "blk": 0, "fgm": 0, "fga": 0, "fg3m": 0, "fg3a": 0, "ftm": 0, "fta": 0, "pf": 0, "tov": 0}}, {"minute": 4, "onCourt": false, "fullMinute": false, "onCourtSeconds": 0.0, "plusMinus": 0, "pts": 0, "stats": {"pts": 0, "reb": 0, "ast": 0, "stl": 0, "blk": 0, "fgm": 0, "fga": 0, "fg3m": 0, "fg3a": 0, "ftm": 0, "fta": 0, "pf": 0, "tov": 0}}, {"minute": 5, "onCourt": false, "fullMinute": false, "onCourtSeconds": 0.0, "plusMinus": 0, "pts": 0, "stats": {"pts": 0, "reb": 0, "ast": 0, "stl": 0, "blk": 0, "fgm": 0, "fga": 0, "fg3m": 0, "fg3a": 0, "ftm": 0, "fta": 0, "pf": 0, "tov": 0}}, {"minute": 6, "onCourt": false, "fullMinute": false, "onCourtSeconds": 0.0, "plusMinus": 0, "pts": 0, "stats": {"pts": 0, "reb": 0, "ast": 0, "stl": 0, "blk": 0, "fgm": 0, "fga": 0, "fg3m": 0, "fg3a": 0, "ftm": 0, "fta": 0, "pf": 0, "tov": 0}}, {"minute": 7, "onCourt": false, "fullMinute": false, "onCourtSeconds": 0.0, "plusMinus": 0, "pts": 0, "stats": {"pts": 0, "reb": 0, "ast": 0, "stl": 0, "blk": 0, "fgm": 0, "fga": 0, "fg3m": 0, "fg3a": 0, "ftm": 0, "fta": 0, "pf": 0, "tov": 0}}, {"minute": 8, "onCourt": false, "fullMinute": false, "onCourtSeconds": 0.0, "plusMinus": 0, "pts": 0, "stats": {"pts": 0, "reb": 0, "ast": 0, "stl": 0, "blk": 0, "fgm": 0, "fga": 0, "fg3m": 0, "fg3a": 0, "ftm": 0, "fta": 0, "pf": 0, "tov": 0}}, {"minute": 9, "onCourt": false, "fullMinute": false, "onCourtSeconds": 0.0, "plusMinus": 0, "pts": 0, "stats": {"pts": 0, "reb": 0, "ast": 0, "stl": 0, "blk": 0, "fgm": 0, "fga": 0, "fg3m": 0, "fg3a": 0, "ftm": 0, "fta": 0, "pf": 0, "tov": 0}}, {"minute": 10, "onCourt": false, "fullMinute": false, "onCourtSeconds": 0.0, "plusMinus": 0, "pts": 0, "stats": {"pts": 0, "reb": 0, "ast": 0, "stl": 0, "blk": 0, "fgm": 0, "fga": 0, "fg3m": 0, "fg3a": 0, "ftm": 0, "fta": 0, "pf": 0, "tov": 0}}, {"minute": 11, "onCourt": false, "fullMinute": false, "onCourtSeconds": 0.0, "plusMinus": 0, "pts": 0, "stats": {"pts": 0, "reb": 0, "ast": 0, "stl": 0, "blk": 0, "fgm": 0, "fga": 0, "fg3m": 0, "fg3a": 0, "ftm": 0, "fta": 0, "pf": 0, "tov": 0}}, {"minute": 12, "onCourt": false, "fullMinute": false, "onCourtSeconds": 0.0, "plusMinus": 0, "pts": 0, "stats": {"pts": 0, "reb": 0, "ast": 0, "stl": 0, "blk": 0, "fgm": 0, "fga": 0, "fg3m": 0, "fg3a": 0, "ftm": 0, "fta": 0, "pf": 0, "tov": 0}}, {"minute": 13, "onCourt": false, "fullMinute": false, "onCourtSeconds": 0.0, "plusMinus": 0, "pts": 0, "stats": {"pts": 0, "reb": 0, "ast": 0, "stl": 0, "blk": 0, "fgm": 0, "fga": 0, "fg3m": 0, "fg3a": 0, "ftm": 0, "fta": 0, "pf": 0, "tov": 0}}, {"minute": 14, "onCourt": false, "fullMinute": false, "onCourtSeconds": 0.0, "plusMinus": 0, "pts": 0, "stats": {"pts": 0, "reb": 0, "ast": 0, "stl": 0, "blk": 0, "fgm": 0, "fga": 0, "fg3m": 0, "fg3a": 0, "ftm": 0, "fta": 0, "pf": 0, "tov": 0}}, {"minute": 15, "onCourt": false, "fullMinute": false, "onCourtSeconds": 0.0, "plusMinus": 0, "pts": 0, "stats": {"pts": 0, "reb": 0, "ast": 0, "stl": 0, "blk": 0, "fgm": 0, "fga": 0, "fg3m": 0, "fg3a": 0, "ftm": 0, "fta": 0, "pf": 0, "tov": 0}}, {"minute": 16, "onCourt": false, "fullMinute": false, "onCourtSeconds": 0.0, "plusMinus": 0, "pts": 0, "stats": {"pts": 0, "reb": 0, "ast": 0, "stl": 0, "blk": 0, "fgm": 0, "fga": 0, "fg3m": 0, "fg3a": 0, "ftm": 0, "fta": 0, "pf": 0, "tov": 0}}, {"minute": 17, "onCourt": false, "fullMinute": false, "onCourtSeconds": 0.0, "plusMinus": 0, "pts": 0, "stats": {"pts": 0, "reb": 0, "ast": 0, "stl": 0, "blk": 0, "fgm": 0, "fga": 0, "fg3m": 0, "fg3a": 0, "ftm": 0, "fta": 0, "pf": 0, "tov": 0}}, {"minute": 18, "onCourt": false, "fullMinute": false, "onCourtSeconds": 0.0, "plusMinus": 0, "pts": 0, "stats": {"pts": 0, "reb": 0, "ast": 0, "stl": 0, "blk": 0, "fgm": 0, "fga": 0, "fg3m": 0, "fg3a": 0, "ftm": 0, "fta": 0, "pf": 0, "tov": 0}}, {"minute": 19, "onCourt": true, "fullMinute": false, "onCourtSeconds": 16.0, "plusMinus": 2, "pts": 0, "stats": {"pts": 0, "reb": 0, "ast": 0, "stl": 0, "blk": 0, "fgm": 0, "fga": 0, "fg3m": 0, "fg3a": 0, "ftm": 0, "fta": 0, "pf": 0, "tov": 0}}, {"minute": 20, "onCourt": false, "fullMinute": false, "onCourtSeconds": 0.0, "plusMinus": 0, "pts": 0, "stats": {"pts": 0, "reb": 0, "ast": 0, "stl": 0, "blk": 0, "fgm": 0, "fga": 0, "fg3m": 0, "fg3a": 0, "ftm": 0, "fta": 0, "pf": 0, "tov": 0}}, {"minute": 21, "onCourt": false, "fullMinute": false, "onCourtSeconds": 0.0, "plusMinus": 0, "pts": 0, "stats": {"pts": 0, "reb": 0, "ast": 0, "stl": 0, "blk": 0, "fgm": 0, "fga": 0, "fg3m": 0, "fg3a": 0, "ftm": 0, "fta": 0, "pf": 0, "tov": 0}}, {"minute": 22, "onCourt": false, "fullMinute": false, "onCourtSeconds": 0.0, "plusMinus": 0, "pts": 0, "stats": {"pts": 0, "reb": 0, "ast": 0, "stl": 0, "blk": 0, "fgm": 0, "fga": 0, "fg3m": 0, "fg3a": 0, "ftm": 0, "fta": 0, "pf": 0, "tov": 0}}, {"minute": 23, "onCourt": false, "fullMinute": false, "onCourtSeconds": 0.0, "plusMinus": 0, "pts": 0, "stats": {"pts": 0, "reb": 0, "ast": 0, "stl": 0, "blk": 0, "fgm": 0, "fga": 0, "fg3m": 0, "fg3a": 0, "ftm": 0, "fta": 0, "pf": 0, "tov": 0}}, {"minute": 24, "onCourt": false, "fullMinute": false, "onCourtSeconds": 0.0, "plusMinus": 0, "pts": 0, "stats": {"pts": 0, "reb": 0, "ast": 0, "stl": 0, "blk": 0, "fgm": 0, "fga": 0, "fg3m": 0, "fg3a": 0, "ftm": 0, "fta": 0, "pf": 0, "tov": 0}}, {"minute": 25, "onCourt": false, "fullMinute": false, "onCourtSeconds": 0.0, "plusMinus": 0, "pts": 0, "stats": {"pts": 0, "reb": 0, "ast": 0, "stl": 0, "blk": 0, "fgm": 0, "fga": 0, "fg3m": 0, "fg3a": 0, "ftm": 0, "fta": 0, "pf": 0, "tov": 0}}, {"minute": 26, "onCourt": false, "fullMinute": false, "onCourtSeconds": 0.0, "plusMinus": 0, "pts": 0, "stats": {"pts": 0, "reb": 0, "ast": 0, "stl": 0, "blk": 0, "fgm": 0, "fga": 0, "fg3m": 0, "fg3a": 0, "ftm": 0, "fta": 0, "pf": 0, "tov": 0}}, {"minute": 27, "onCourt": false, "fullMinute": false, "onCourtSeconds": 0.0, "plusMinus": 0, "pts": 0, "stats": {"pts": 0, "reb": 0, "ast": 0, "stl": 0, "blk": 0, "fgm": 0, "fga": 0, "fg3m": 0, "fg3a": 0, "ftm": 0, "fta": 0, "pf": 0, "tov": 0}}, {"minute": 28, "onCourt": false, "fullMinute": false, "onCourtSeconds": 0.0, "plusMinus": 0, "pts": 0, "stats": {"pts": 0, "reb": 0, "ast": 0, "stl": 0, "blk": 0, "fgm": 0, "fga": 0, "fg3m": 0, "fg3a": 0, "ftm": 0, "fta": 0, "pf": 0, "tov": 0}}, {"minute": 29, "onCourt": false, "fullMinute": false, "onCourtSeconds": 0.0, "plusMinus": 0, "pts": 0, "stats": {"pts": 0, "reb": 0, "ast": 0, "stl": 0, "blk": 0, "fgm": 0, "fga": 0, "fg3m": 0, "fg3a": 0, "ftm": 0, "fta": 0, "pf": 0, "tov": 0}}, {"minute": 30, "onCourt": false, "fullMinute": false, "onCourtSeconds": 0.0, "plusMinus": 0, "pts": 0, "stats": {"pts": 0, "reb": 0, "ast": 0, "stl": 0, "blk": 0, "fgm": 0, "fga": 0, "fg3m": 0, "fg3a": 0, "ftm": 0, "fta": 0, "pf": 0, "tov": 0}}, {"minute": 31, "onCourt": false, "fullMinute": false, "onCourtSeconds": 0.0, "plusMinus": 0, "pts": 0, "stats": {"pts": 0, "reb": 0, "ast": 0, "stl": 0, "blk": 0, "fgm": 0, "fga": 0, "fg3m": 0, "fg3a": 0, "ftm": 0, "fta": 0, "pf": 0, "tov": 0}}, {"minute": 32, "onCourt": false, "fullMinute": false, "onCourtSeconds": 0.0, "plusMinus": 0, "pts": 0, "stats": {"pts": 0, "reb": 0, "ast": 0, "stl": 0, "blk": 0, "fgm": 0, "fga": 0, "fg3m": 0, "fg3a": 0, "ftm": 0, "fta": 0, "pf": 0, "tov": 0}}, {"minute": 33, "onCourt": false, "fullMinute": false, "onCourtSeconds": 0.0, "plusMinus": 0, "pts": 0, "stats": {"pts": 0, "reb": 0, "ast": 0, "stl": 0, "blk": 0, "fgm": 0, "fga": 0, "fg3m": 0, "fg3a": 0, "ftm": 0, "fta": 0, "pf": 0, "tov": 0}}, {"minute": 34, "onCourt": false, "fullMinute": false, "onCourtSeconds": 0.0, "plusMinus": 0, "pts": 0, "stats": {"pts": 0, "reb": 0, "ast": 0, "stl": 0, "blk": 0, "fgm": 0, "fga": 0, "fg3m": 0, "fg3a": 0, "ftm": 0, "fta": 0, "pf": 0, "tov": 0}}, {"minute": 35, "onCourt": false, "fullMinute": false, "onCourtSeconds": 0.0, "plusMinus": 0, "pts": 0, "stats": {"pts": 0, "reb": 0, "ast": 0, "stl": 0, "blk": 0, "fgm": 0, "fga": 0, "fg3m": 0, "fg3a": 0, "ftm": 0, "fta": 0, "pf": 0, "tov": 0}}, {"minute": 36, "onCourt": false, "fullMinute": false, "onCourtSeconds": 0.0, "plusMinus": 0, "pts": 0, "stats": {"pts": 0, "reb": 0, "ast": 0, "stl": 0, "blk": 0, "fgm": 0, "fga": 0, "fg3m": 0, "fg3a": 0, "ftm": 0, "fta": 0, "pf": 0, "tov": 0}}, {"minute": 37, "onCourt": false, "fullMinute": false, "onCourtSeconds": 0.0, "plusMinus": 0, "pts": 0, "stats": {"pts": 0, "reb": 0, "ast": 0, "stl": 0, "blk": 0, "fgm": 0, "fga": 0, "fg3m": 0, "fg3a": 0, "ftm": 0, "fta": 0, "pf": 0, "tov": 0}}, {"minute": 38, "onCourt": false, "fullMinute": false, "onCourtSeconds": 0.0, "plusMinus": 0, "pts": 0, "stats": {"pts": 0, "reb": 0, "ast": 0, "stl": 0, "blk": 0, "fgm": 0, "fga": 0, "fg3m": 0, "fg3a": 0, "ftm": 0, "fta": 0, "pf": 0, "tov": 0}}, {"minute": 39, "onCourt": false, "fullMinute": false, "onCourtSeconds": 0.0, "plusMinus": 0, "pts": 0, "stats": {"pts": 0, "reb": 0, "ast": 0, "stl": 0, "blk": 0, "fgm": 0, "fga": 0, "fg3m": 0, "fg3a": 0, "ftm": 0, "fta": 0, "pf": 0, "tov": 0}}], "gameStats": {"pts": 0, "reb": 0, "ast": 0, "stl": 0, "blk": 0, "fgm": 0, "fga": 0, "fg3m": 0, "fg3a": 0, "ftm": 0, "fta": 0, "pf": 1, "tov": 0}, "totalPlusMinus": 2}, {"gameId": "2805264", "date": "2026-02-17", "teamCode": "SKS", "teamName": "SK Slavia Praha", "opponent": "BK GAPA Hradec Kr\u00e1lov\u00e9", "isHome": true, "score": "79:68", "numOT": 0, "isDNP": false, "totalSeconds": 457.0, "periods": [{"period": 1, "label": "Q1", "startMinute": 0, "endMinute": 10, "duration": 10}, {"period": 2, "label": "Q2", "startMinute": 10, "endMinute": 20, "duration": 10}, {"period": 3, "label": "Q3", "startMinute": 20, "endMinute": 30, "duration": 10}, {"period": 4, "label": "Q4", "startMinute": 30, "endMinute": 40, "duration": 10}], "minutes": [{"minute": 0, "onCourt": false, "fullMinute": false, "onCourtSeconds": 0.0, "plusMinus": 0, "pts": 0, "stats": {"pts": 0, "reb": 0, "ast": 0, "stl": 0, "blk": 0, "fgm": 0, "fga": 0, "fg3m": 0, "fg3a": 0, "ftm": 0, "fta": 0, "pf": 0, "tov": 0}}, {"minute": 1, "onCourt": false, "fullMinute": false, "onCourtSeconds": 0.0, "plusMinus": 0, "pts": 0, "stats": {"pts": 0, "reb": 0, "ast": 0, "stl": 0, "blk": 0, "fgm": 0, "fga": 0, "fg3m": 0, "fg3a": 0, "ftm": 0, "fta": 0, "pf": 0, "tov": 0}}, {"minute": 2, "onCourt": false, "fullMinute": false, "onCourtSeconds": 0.0, "plusMinus": 0, "pts": 0, "stats": {"pts": 0, "reb": 0, "ast": 0, "stl": 0, "blk": 0, "fgm": 0, "fga": 0, "fg3m": 0, "fg3a": 0, "ftm": 0, "fta": 0, "pf": 0, "tov": 0}}, {"minute": 3, "onCourt": false, "fullMinute": false, "onCourtSeconds": 0.0, "plusMinus": 0, "pts": 0, "stats": {"pts": 0, "reb": 0, "ast": 0, "stl": 0, "blk": 0, "fgm": 0, "fga": 0, "fg3m": 0, "fg3a": 0, "ftm": 0, "fta": 0, "pf": 0, "tov": 0}}, {"minute": 4, "onCourt": false, "fullMinute": false, "onCourtSeconds": 0.0, "plusMinus": 0, "pts": 0, "stats": {"pts": 0, "reb": 0, "ast": 0, "stl": 0, "blk": 0, "fgm": 0, "fga": 0, "fg3m": 0, "fg3a": 0, "ftm": 0, "fta": 0, "pf": 0, "tov": 0}}, {"minute": 5, "onCourt": false, "fullMinute": false, "onCourtSeconds": 0.0, "plusMinus": 0, "pts": 0, "stats": {"pts": 0, "reb": 0, "ast": 0, "stl": 0, "blk": 0, "fgm": 0, "fga": 0, "fg3m": 0, "fg3a": 0, "ftm": 0, "fta": 0, "pf": 0, "tov": 0}}, {"minute": 6, "onCourt": false, "fullMinute": false, "onCourtSeconds": 0.0, "plusMinus": 0, "pts": 0, "stats": {"pts": 0, "reb": 0, "ast": 0, "stl": 0, "blk": 0, "fgm": 0, "fga": 0, "fg3m": 0, "fg3a": 0, "ftm": 0, "fta": 0, "pf": 0, "tov": 0}}, {"minute": 7, "onCourt": true, "fullMinute": false, "onCourtSeconds": 14.0, "plusMinus": -1, "pts": 0, "stats": {"pts": 0, "reb": 0, "ast": 0, "stl": 0, "blk": 0, "fgm": 0, "fga": 0, "fg3m": 0, "fg3a": 0, "ftm": 0, "fta": 0, "pf": 0, "tov": 0}}, {"minute": 8, "onCourt": true, "fullMinute": true, "onCourtSeconds": 60.0, "plusMinus": 0, "pts": 0, "stats": {"pts": 0, "reb": 0, "ast": 0, "stl": 0, "blk": 0, "fgm": 0, "fga": 1, "fg3m": 0, "fg3a": 0, "ftm": 0, "fta": 0, "pf": 0, "tov": 0}}, {"minute": 9, "onCourt": true, "fullMinute": true, "onCourtSeconds": 60.0, "plusMinus": 0, "pts": 0, "stats": {"pts": 0, "reb": 0, "ast": 0, "stl": 0, "blk": 0, "fgm": 0, "fga": 0, "fg3m": 0, "fg3a": 0, "ftm": 0, "fta": 0, "pf": 0, "tov": 0}}, {"minute": 10, "onCourt": true, "fullMinute": true, "onCourtSeconds": 60.0, "plusMinus": 0, "pts": 0, "stats": {"pts": 0, "reb": 0, "ast": 0, "stl": 0, "blk": 0, "fgm": 0, "fga": 0, "fg3m": 0, "fg3a": 0, "ftm": 0, "fta": 0, "pf": 0, "tov": 0}}, {"minute": 11, "onCourt": true, "fullMinute": true, "onCourtSeconds": 60.0, "plusMinus": -3, "pts": 0, "stats": {"pts": 0, "reb": 0, "ast": 0, "stl": 0, "blk": 0, "fgm": 0, "fga": 0, "fg3m": 0, "fg3a": 0, "ftm": 0, "fta": 0, "pf": 0, "tov": 0}}, {"minute": 12, "onCourt": true, "fullMinute": false, "onCourtSeconds": 7.0, "plusMinus": 0, "pts": 0, "stats": {"pts": 0, "reb": 0, "ast": 0, "stl": 0, "blk": 0, "fgm": 0, "fga": 0, "fg3m": 0, "fg3a": 0, "ftm": 0, "fta": 0, "pf": 0, "tov": 0}}, {"minute": 13, "onCourt": false, "fullMinute": false, "onCourtSeconds": 0.0, "plusMinus": 0, "pts": 0, "stats": {"pts": 0, "reb": 0, "ast": 0, "stl": 0, "blk": 0, "fgm": 0, "fga": 0, "fg3m": 0, "fg3a": 0, "ftm": 0, "fta": 0, "pf": 0, "tov": 0}}, {"minute": 14, "onCourt": false, "fullMinute": false, "onCourtSeconds": 0.0, "plusMinus": 0, "pts": 0, "stats": {"pts": 0, "reb": 0, "ast": 0, "stl": 0, "blk": 0, "fgm": 0, "fga": 0, "fg3m": 0, "fg3a": 0, "ftm": 0, "fta": 0, "pf": 0, "tov": 0}}, {"minute": 15, "onCourt": false, "fullMinute": false, "onCourtSeconds": 0.0, "plusMinus": 0, "pts": 0, "stats": {"pts": 0, "reb": 0, "ast": 0, "stl": 0, "blk": 0, "fgm": 0, "fga": 0, "fg3m": 0, "fg3a": 0, "ftm": 0, "fta": 0, "pf": 0, "tov": 0}}, {"minute": 16, "onCourt": false, "fullMinute": false, "onCourtSeconds": 0.0, "plusMinus": 0, "pts": 0, "stats": {"pts": 0, "reb": 0, "ast": 0, "stl": 0, "blk": 0, "fgm": 0, "fga": 0, "fg3m": 0, "fg3a": 0, "ftm": 0, "fta": 0, "pf": 0, "tov": 0}}, {"minute": 17, "onCourt": false, "fullMinute": false, "onCourtSeconds": 0.0, "plusMinus": 0, "pts": 0, "stats": {"pts": 0, "reb": 0, "ast": 0, "stl": 0, "blk": 0, "fgm": 0, "fga": 0, "fg3m": 0, "fg3a": 0, "ftm": 0, "fta": 0, "pf": 0, "tov": 0}}, {"minute": 18, "onCourt": false, "fullMinute": false, "onCourtSeconds": 0.0, "plusMinus": 0, "pts": 0, "stats": {"pts": 0, "reb": 0, "ast": 0, "stl": 0, "blk": 0, "fgm": 0, "fga": 0, "fg3m": 0, "fg3a": 0, "ftm": 0, "fta": 0, "pf": 0, "tov": 0}}, {"minute": 19, "onCourt": true, "fullMinute": false, "onCourtSeconds": 32.0, "plusMinus": -2, "pts": 0, "stats": {"pts": 0, "reb": 0, "ast": 0, "stl": 0, "blk": 0, "fgm": 0, "fga": 0, "fg3m": 0, "fg3a": 0, "ftm": 0, "fta": 0, "pf": 0, "tov": 0}}, {"minute": 20, "onCourt": false, "fullMinute": false, "onCourtSeconds": 0.0, "plusMinus": 0, "pts": 0, "stats": {"pts": 0, "reb": 0, "ast": 0, "stl": 0, "blk": 0, "fgm": 0, "fga": 0, "fg3m": 0, "fg3a": 0, "ftm": 0, "fta": 0, "pf": 0, "tov": 0}}, {"minute": 21, "onCourt": false, "fullMinute": false, "onCourtSeconds": 0.0, "plusMinus": 0, "pts": 0, "stats": {"pts": 0, "reb": 0, "ast": 0, "stl": 0, "blk": 0, "fgm": 0, "fga": 0, "fg3m": 0, "fg3a": 0, "ftm": 0, "fta": 0, "pf": 0, "tov": 0}}, {"minute": 22, "onCourt": false, "fullMinute": false, "onCourtSeconds": 0.0, "plusMinus": 0, "pts": 0, "stats": {"pts": 0, "reb": 0, "ast": 0, "stl": 0, "blk": 0, "fgm": 0, "fga": 0, "fg3m": 0, "fg3a": 0, "ftm": 0, "fta": 0, "pf": 0, "tov": 0}}, {"minute": 23, "onCourt": false, "fullMinute": false, "onCourtSeconds": 0.0, "plusMinus": 0, "pts": 0, "stats": {"pts": 0, "reb": 0, "ast": 0, "stl": 0, "blk": 0, "fgm": 0, "fga": 0, "fg3m": 0, "fg3a": 0, "ftm": 0, "fta": 0, "pf": 0, "tov": 0}}, {"minute": 24, "onCourt": false, "fullMinute": false, "onCourtSeconds": 0.0, "plusMinus": 0, "pts": 0, "stats": {"pts": 0, "reb": 0, "ast": 0, "stl": 0, "blk": 0, "fgm": 0, "fga": 0, "fg3m": 0, "fg3a": 0, "ftm": 0, "fta": 0, "pf": 0, "tov": 0}}, {"minute": 25, "onCourt": false, "fullMinute": false, "onCourtSeconds": 0.0, "plusMinus": 0, "pts": 0, "stats": {"pts": 0, "reb": 0, "ast": 0, "stl": 0, "blk": 0, "fgm": 0, "fga": 0, "fg3m": 0, "fg3a": 0, "ftm": 0, "fta": 0, "pf": 0, "tov": 0}}, {"minute": 26, "onCourt": false, "fullMinute": false, "onCourtSeconds": 0.0, "plusMinus": 0, "pts": 0, "stats": {"pts": 0, "reb": 0, "ast": 0, "stl": 0, "blk": 0, "fgm": 0, "fga": 0, "fg3m": 0, "fg3a": 0, "ftm": 0, "fta": 0, "pf": 0, "tov": 0}}, {"minute": 27, "onCourt": false, "fullMinute": false, "onCourtSeconds": 0.0, "plusMinus": 0, "pts": 0, "stats": {"pts": 0, "reb": 0, "ast": 0, "stl": 0, "blk": 0, "fgm": 0, "fga": 0, "fg3m": 0, "fg3a": 0, "ftm": 0, "fta": 0, "pf": 0, "tov": 0}}, {"minute": 28, "onCourt": true, "fullMinute": false, "onCourtSeconds": 29.0, "plusMinus": 2, "pts": 0, "stats": {"pts": 0, "reb": 0, "ast": 0, "stl": 0, "blk": 0, "fgm": 0, "fga": 0, "fg3m": 0, "fg3a": 0, "ftm": 0, "fta": 0, "pf": 0, "tov": 0}}, {"minute": 29, "onCourt": true, "fullMinute": true, "onCourtSeconds": 60.0, "plusMinus": -2, "pts": 0, "stats": {"pts": 0, "reb": 0, "ast": 0, "stl": 0, "blk": 0, "fgm": 0, "fga": 1, "fg3m": 0, "fg3a": 0, "ftm": 0, "fta": 0, "pf": 0, "tov": 0}}, {"minute": 30, "onCourt": false, "fullMinute": false, "onCourtSeconds": 0.0, "plusMinus": 0, "pts": 0, "stats": {"pts": 0, "reb": 0, "ast": 0, "stl": 0, "blk": 0, "fgm": 0, "fga": 0, "fg3m": 0, "fg3a": 0, "ftm": 0, "fta": 0, "pf": 0, "tov": 0}}, {"minute": 31, "onCourt": false, "fullMinute": false, "onCourtSeconds": 0.0, "plusMinus": 0, "pts": 0, "stats": {"pts": 0, "reb": 0, "ast": 0, "stl": 0, "blk": 0, "fgm": 0, "fga": 0, "fg3m": 0, "fg3a": 0, "ftm": 0, "fta": 0, "pf": 0, "tov": 0}}, {"minute": 32, "onCourt": false, "fullMinute": false, "onCourtSeconds": 0.0, "plusMinus": 0, "pts": 0, "stats": {"pts": 0, "reb": 0, "ast": 0, "stl": 0, "blk": 0, "fgm": 0, "fga": 0, "fg3m": 0, "fg3a": 0, "ftm": 0, "fta": 0, "pf": 0, "tov": 0}}, {"minute": 33, "onCourt": false, "fullMinute": false, "onCourtSeconds": 0.0, "plusMinus": 0, "pts": 0, "stats": {"pts": 0, "reb": 0, "ast": 0, "stl": 0, "blk": 0, "fgm": 0, "fga": 0, "fg3m": 0, "fg3a": 0, "ftm": 0, "fta": 0, "pf": 0, "tov": 0}}, {"minute": 34, "onCourt": false, "fullMinute": false, "onCourtSeconds": 0.0, "plusMinus": 0, "pts": 0, "stats": {"pts": 0, "reb": 0, "ast": 0, "stl": 0, "blk": 0, "fgm": 0, "fga": 0, "fg3m": 0, "fg3a": 0, "ftm": 0, "fta": 0, "pf": 0, "tov": 0}}, {"minute": 35, "onCourt": false, "fullMinute": false, "onCourtSeconds": 0.0, "plusMinus": 0, "pts": 0, "stats": {"pts": 0, "reb": 0, "ast": 0, "stl": 0, "blk": 0, "fgm": 0, "fga": 0, "fg3m": 0, "fg3a": 0, "ftm": 0, "fta": 0, "pf": 0, "tov": 0}}, {"minute": 36, "onCourt": false, "fullMinute": false, "onCourtSeconds": 0.0, "plusMinus": 0, "pts": 0, "stats": {"pts": 0, "reb": 0, "ast": 0, "stl": 0, "blk": 0, "fgm": 0, "fga": 0, "fg3m": 0, "fg3a": 0, "ftm": 0, "fta": 0, "pf": 0, "tov": 0}}, {"minute": 37, "onCourt": false, "fullMinute": false, "onCourtSeconds": 0.0, "plusMinus": 0, "pts": 0, "stats": {"pts": 0, "reb": 0, "ast": 0, "stl": 0, "blk": 0, "fgm": 0, "fga": 0, "fg3m": 0, "fg3a": 0, "ftm": 0, "fta": 0, "pf": 0, "tov": 0}}, {"minute": 38, "onCourt": true, "fullMinute": false, "onCourtSeconds": 15.0, "plusMinus": -2, "pts": 0, "stats": {"pts": 0, "reb": 0, "ast": 0, "stl": 0, "blk": 0, "fgm": 0, "fga": 0, "fg3m": 0, "fg3a": 0, "ftm": 0, "fta": 0, "pf": 0, "tov": 0}}, {"minute": 39, "onCourt": true, "fullMinute": true, "onCourtSeconds": 60.0, "plusMinus": -2, "pts": 0, "stats": {"pts": 0, "reb": 0, "ast": 0, "stl": 0, "blk": 0, "fgm": 0, "fga": 0, "fg3m": 0, "fg3a": 0, "ftm": 0, "fta": 0, "pf": 0, "tov": 0}}], "gameStats": {"pts": 0, "reb": 0, "ast": 0, "stl": 0, "blk": 0, "fgm": 0, "fga": 2, "fg3m": 0, "fg3a": 0, "ftm": 0, "fta": 0, "pf": 1, "tov": 0}, "totalPlusMinus": -10}]}