{"teamName": "BK Opava", "teamCode": "OPA", "slug": "bk-opava", "season": "2025-26", "players": [{"firstName": "Clevon", "familyName": "Brown Jr", "playerSlug": "bk-opava-clevon-brown-jr", "gp": 26, "seasonTotals": {"pts": 329, "reb": 193, "ast": 29, "stl": 17, "blk": 36, "fgm": 131, "fga": 221, "fg3m": 26, "fg3a": 65, "ftm": 41, "fta": 61, "tov": 45, "pf": 55, "gp": 26, "totalSeconds": 42684.0, "plusMinus": 78}, "seasonAverages": {"minPerGame": "27:21", "pts": 12.7, "reb": 7.4, "ast": 1.1, "stl": 0.7, "blk": 1.4, "fgPct": 59.3, "fg3Pct": 40.0, "ftPct": 67.2, "tov": 1.7, "pf": 2.1, "plusMinus": 3.0}}, {"firstName": "Wesley Lavon", "familyName": "Person Jr", "playerSlug": "bk-opava-wesley-lavon-person-jr", "gp": 22, "seasonTotals": {"pts": 406, "reb": 78, "ast": 41, "stl": 18, "blk": 1, "fgm": 142, "fga": 315, "fg3m": 51, "fg3a": 148, "ftm": 71, "fta": 87, "tov": 25, "pf": 54, "gp": 22, "totalSeconds": 36862.0, "plusMinus": 29}, "seasonAverages": {"minPerGame": "27:55", "pts": 18.5, "reb": 3.5, "ast": 1.9, "stl": 0.8, "blk": 0.0, "fgPct": 45.1, "fg3Pct": 34.5, "ftPct": 81.6, "tov": 1.1, "pf": 2.5, "plusMinus": 1.3}}, {"firstName": "\u0160imon", "familyName": "Pur\u0161l", "playerSlug": "bk-opava-simon-pursl", "gp": 24, "seasonTotals": {"pts": 268, "reb": 170, "ast": 46, "stl": 12, "blk": 13, "fgm": 99, "fga": 196, "fg3m": 1, "fg3a": 15, "ftm": 69, "fta": 121, "tov": 35, "pf": 60, "gp": 24, "totalSeconds": 34653.0, "plusMinus": 1}, "seasonAverages": {"minPerGame": "24:03", "pts": 11.2, "reb": 7.1, "ast": 1.9, "stl": 0.5, "blk": 0.5, "fgPct": 50.5, "fg3Pct": 6.7, "ftPct": 57.0, "tov": 1.5, "pf": 2.5, "plusMinus": 0.0}}, {"firstName": "Jan", "familyName": "\u0160vandrl\u00edk", "playerSlug": "bk-opava-jan-svandrlik", "gp": 26, "seasonTotals": {"pts": 222, "reb": 95, "ast": 23, "stl": 19, "blk": 6, "fgm": 75, "fga": 178, "fg3m": 60, "fg3a": 144, "ftm": 12, "fta": 21, "tov": 10, "pf": 67, "gp": 26, "totalSeconds": 33236.0, "plusMinus": 71}, "seasonAverages": {"minPerGame": "21:18", "pts": 8.5, "reb": 3.7, "ast": 0.9, "stl": 0.7, "blk": 0.2, "fgPct": 42.1, "fg3Pct": 41.7, "ftPct": 57.1, "tov": 0.4, "pf": 2.6, "plusMinus": 2.7}}, {"firstName": "Jakub", "familyName": "\u0160i\u0159ina", "playerSlug": "bk-opava-jakub-sirina", "gp": 24, "seasonTotals": {"pts": 245, "reb": 57, "ast": 97, "stl": 19, "blk": 0, "fgm": 77, "fga": 197, "fg3m": 46, "fg3a": 145, "ftm": 45, "fta": 56, "tov": 43, "pf": 43, "gp": 24, "totalSeconds": 31037.0, "plusMinus": 21}, "seasonAverages": {"minPerGame": "21:33", "pts": 10.2, "reb": 2.4, "ast": 4.0, "stl": 0.8, "blk": 0.0, "fgPct": 39.1, "fg3Pct": 31.7, "ftPct": 80.4, "tov": 1.8, "pf": 1.8, "plusMinus": 0.9}}, {"firstName": "Radovan", "familyName": "Kou\u0159il", "playerSlug": "bk-opava-radovan-kouril", "gp": 21, "seasonTotals": {"pts": 173, "reb": 67, "ast": 144, "stl": 19, "blk": 3, "fgm": 67, "fga": 172, "fg3m": 26, "fg3a": 93, "ftm": 13, "fta": 32, "tov": 43, "pf": 28, "gp": 21, "totalSeconds": 28183.0, "plusMinus": 61}, "seasonAverages": {"minPerGame": "22:22", "pts": 8.2, "reb": 3.2, "ast": 6.9, "stl": 0.9, "blk": 0.1, "fgPct": 39.0, "fg3Pct": 28.0, "ftPct": 40.6, "tov": 2.0, "pf": 1.3, "plusMinus": 2.9}}, {"firstName": "Marek", "familyName": "Vyroubal", "playerSlug": "bk-opava-marek-vyroubal", "gp": 21, "seasonTotals": {"pts": 186, "reb": 40, "ast": 57, "stl": 17, "blk": 3, "fgm": 56, "fga": 134, "fg3m": 24, "fg3a": 75, "ftm": 50, "fta": 76, "tov": 26, "pf": 43, "gp": 21, "totalSeconds": 26351.0, "plusMinus": 122}, "seasonAverages": {"minPerGame": "20:54", "pts": 8.9, "reb": 1.9, "ast": 2.7, "stl": 0.8, "blk": 0.1, "fgPct": 41.8, "fg3Pct": 32.0, "ftPct": 65.8, "tov": 1.2, "pf": 2.0, "plusMinus": 5.8}}, {"firstName": "Jakub", "familyName": "Slav\u00edk", "playerSlug": "bk-opava-jakub-slavik", "gp": 22, "seasonTotals": {"pts": 152, "reb": 111, "ast": 21, "stl": 9, "blk": 0, "fgm": 49, "fga": 120, "fg3m": 9, "fg3a": 39, "ftm": 45, "fta": 62, "tov": 21, "pf": 55, "gp": 22, "totalSeconds": 24677.0, "plusMinus": -3}, "seasonAverages": {"minPerGame": "18:41", "pts": 6.9, "reb": 5.0, "ast": 1.0, "stl": 0.4, "blk": 0.0, "fgPct": 40.8, "fg3Pct": 23.1, "ftPct": 72.6, "tov": 1.0, "pf": 2.5, "plusMinus": -0.1}}, {"firstName": "Kry\u0161tof", "familyName": "Kavan", "playerSlug": "bk-opava-krystof-kavan", "gp": 24, "seasonTotals": {"pts": 87, "reb": 75, "ast": 40, "stl": 16, "blk": 6, "fgm": 37, "fga": 88, "fg3m": 4, "fg3a": 24, "ftm": 9, "fta": 23, "tov": 29, "pf": 58, "gp": 24, "totalSeconds": 19220.0, "plusMinus": 38}, "seasonAverages": {"minPerGame": "13:20", "pts": 3.6, "reb": 3.1, "ast": 1.7, "stl": 0.7, "blk": 0.2, "fgPct": 42.0, "fg3Pct": 16.7, "ftPct": 39.1, "tov": 1.2, "pf": 2.4, "plusMinus": 1.6}}, {"firstName": "Filip", "familyName": "Zbr\u00e1nek", "playerSlug": "bk-opava-filip-zbranek", "gp": 16, "seasonTotals": {"pts": 70, "reb": 24, "ast": 7, "stl": 6, "blk": 1, "fgm": 19, "fga": 63, "fg3m": 10, "fg3a": 46, "ftm": 22, "fta": 31, "tov": 6, "pf": 41, "gp": 16, "totalSeconds": 11064.0, "plusMinus": 9}, "seasonAverages": {"minPerGame": "11:31", "pts": 4.4, "reb": 1.5, "ast": 0.4, "stl": 0.4, "blk": 0.1, "fgPct": 30.2, "fg3Pct": 21.7, "ftPct": 71.0, "tov": 0.4, "pf": 2.6, "plusMinus": 0.6}}, {"firstName": "David", "familyName": "Moty\u010dka", "playerSlug": "bk-opava-david-motycka", "gp": 24, "seasonTotals": {"pts": 60, "reb": 36, "ast": 4, "stl": 3, "blk": 1, "fgm": 24, "fga": 47, "fg3m": 10, "fg3a": 24, "ftm": 2, "fta": 4, "tov": 4, "pf": 23, "gp": 24, "totalSeconds": 10436.0, "plusMinus": -10}, "seasonAverages": {"minPerGame": "7:14", "pts": 2.5, "reb": 1.5, "ast": 0.2, "stl": 0.1, "blk": 0.0, "fgPct": 51.1, "fg3Pct": 41.7, "ftPct": 50.0, "tov": 0.2, "pf": 1.0, "plusMinus": -0.4}}, {"firstName": "Franti\u0161ek", "familyName": "V\u00e1\u0148a", "playerSlug": "bk-opava-frantisek-vana", "gp": 9, "seasonTotals": {"pts": 32, "reb": 9, "ast": 1, "stl": 2, "blk": 0, "fgm": 9, "fga": 36, "fg3m": 8, "fg3a": 32, "ftm": 6, "fta": 8, "tov": 2, "pf": 8, "gp": 9, "totalSeconds": 4656.0, "plusMinus": -14}, "seasonAverages": {"minPerGame": "8:37", "pts": 3.6, "reb": 1.0, "ast": 0.1, "stl": 0.2, "blk": 0.0, "fgPct": 25.0, "fg3Pct": 25.0, "ftPct": 75.0, "tov": 0.2, "pf": 0.9, "plusMinus": -1.6}}, {"firstName": "Isaiah John", "familyName": "Gray", "playerSlug": "bk-opava-isaiah-john-gray", "gp": 3, "seasonTotals": {"pts": 36, "reb": 17, "ast": 16, "stl": 5, "blk": 0, "fgm": 12, "fga": 32, "fg3m": 0, "fg3a": 5, "ftm": 12, "fta": 16, "tov": 8, "pf": 9, "gp": 3, "totalSeconds": 4616.0, "plusMinus": -6}, "seasonAverages": {"minPerGame": "25:38", "pts": 12.0, "reb": 5.7, "ast": 5.3, "stl": 1.7, "blk": 0.0, "fgPct": 37.5, "fg3Pct": 0.0, "ftPct": 75.0, "tov": 2.7, "pf": 3.0, "plusMinus": -2.0}}, {"firstName": "Lud\u011bk", "familyName": "Jure\u010dka", "playerSlug": "bk-opava-ludek-jurecka", "gp": 8, "seasonTotals": {"pts": 18, "reb": 6, "ast": 5, "stl": 1, "blk": 0, "fgm": 5, "fga": 15, "fg3m": 5, "fg3a": 10, "ftm": 3, "fta": 3, "tov": 1, "pf": 3, "gp": 8, "totalSeconds": 3093.0, "plusMinus": -10}, "seasonAverages": {"minPerGame": "6:26", "pts": 2.2, "reb": 0.8, "ast": 0.6, "stl": 0.1, "blk": 0.0, "fgPct": 33.3, "fg3Pct": 50.0, "ftPct": 100.0, "tov": 0.1, "pf": 0.4, "plusMinus": -1.2}}, {"firstName": "P\u0159emysl", "familyName": "Dubov\u00fd", "playerSlug": "bk-opava-premysl-dubovy", "gp": 11, "seasonTotals": {"pts": 10, "reb": 2, "ast": 0, "stl": 2, "blk": 0, "fgm": 3, "fga": 10, "fg3m": 2, "fg3a": 8, "ftm": 2, "fta": 2, "tov": 1, "pf": 6, "gp": 11, "totalSeconds": 1688.0, "plusMinus": -1}, "seasonAverages": {"minPerGame": "2:33", "pts": 0.9, "reb": 0.2, "ast": 0.0, "stl": 0.2, "blk": 0.0, "fgPct": 30.0, "fg3Pct": 25.0, "ftPct": 100.0, "tov": 0.1, "pf": 0.5, "plusMinus": -0.1}}, {"firstName": "Pavel", "familyName": "Czudek", "playerSlug": "bk-opava-pavel-czudek", "gp": 11, "seasonTotals": {"pts": 0, "reb": 3, "ast": 1, "stl": 0, "blk": 0, "fgm": 0, "fga": 2, "fg3m": 0, "fg3a": 2, "ftm": 0, "fta": 0, "tov": 1, "pf": 2, "gp": 11, "totalSeconds": 416.0, "plusMinus": -2}, "seasonAverages": {"minPerGame": "0:37", "pts": 0.0, "reb": 0.3, "ast": 0.1, "stl": 0.0, "blk": 0.0, "fgPct": 0.0, "fg3Pct": 0.0, "ftPct": 0.0, "tov": 0.1, "pf": 0.2, "plusMinus": -0.2}}, {"firstName": "Pavel", "familyName": "Ka\u0161til", "playerSlug": "bk-opava-pavel-kastil", "gp": 6, "seasonTotals": {"pts": 3, "reb": 0, "ast": 0, "stl": 0, "blk": 0, "fgm": 1, "fga": 2, "fg3m": 1, "fg3a": 1, "ftm": 0, "fta": 0, "tov": 0, "pf": 0, "gp": 6, "totalSeconds": 296.0, "plusMinus": 3}, "seasonAverages": {"minPerGame": "0:49", "pts": 0.5, "reb": 0.0, "ast": 0.0, "stl": 0.0, "blk": 0.0, "fgPct": 50.0, "fg3Pct": 100.0, "ftPct": 0.0, "tov": 0.0, "pf": 0.0, "plusMinus": 0.5}}, {"firstName": "Jan", "familyName": "P\u0159ececht\u011bl", "playerSlug": "bk-opava-jan-precechtel", "gp": 4, "seasonTotals": {"pts": 0, "reb": 0, "ast": 0, "stl": 0, "blk": 0, "fgm": 0, "fga": 0, "fg3m": 0, "fg3a": 0, "ftm": 0, "fta": 0, "tov": 0, "pf": 0, "gp": 4, "totalSeconds": 0, "plusMinus": 0}, "seasonAverages": {"minPerGame": "0:00", "pts": 0.0, "reb": 0.0, "ast": 0.0, "stl": 0.0, "blk": 0.0, "fgPct": 0.0, "fg3Pct": 0.0, "ftPct": 0.0, "tov": 0.0, "pf": 0.0, "plusMinus": 0.0}}]}