[{"first_name": "Bar", "family_name": "Amiel", "slug": "era-basketball-nymburk-bar-amiel", "season": "2025-26", "team": "ERA Basketball Nymburk", "on_min": 6, "on_ortg": 206.6, "on_drtg": 85.9, "on_net": 120.7, "off_min": 32, "off_ortg": 116.9, "off_drtg": 79.9, "off_net": 37.0, "delta_net": 83.7}, {"first_name": "Matej", "family_name": "Koza", "slug": "nh-ostrava-matej-koza", "season": "2025-26", "team": "NH Ostrava", "on_min": 2, "on_ortg": 184.4, "on_drtg": 69.4, "on_net": 115.0, "off_min": 38, "off_ortg": 103.4, "off_drtg": 130.5, "off_net": -27.1, "delta_net": 142.1}, {"first_name": "Vladimír", "family_name": "Vondra", "slug": "bk-kvis-pardubice-vladimir-vondra", "season": "2025-26", "team": "BK KVIS Pardubice", "on_min": 11, "on_ortg": 127.5, "on_drtg": 68.1, "on_net": 59.4, "off_min": 108, "off_ortg": 150.2, "off_drtg": 109.7, "off_net": 40.5, "delta_net": 18.9}, {"first_name": "Marcus Armani", "family_name": "Santos - Silva", "slug": "era-basketball-nymburk-marcus-armani-santos-silva", "season": "2025-26", "team": "ERA Basketball Nymburk", "on_min": 236, "on_ortg": 147.8, "on_drtg": 91.8, "on_net": 56.0, "off_min": 354, "off_ortg": 128.0, "off_drtg": 103.6, "off_net": 24.4, "delta_net": 31.6}, {"first_name": "Jay", "family_name": "Shumate", "slug": "era-basketball-nymburk-jay-shumate", "season": "2025-26", "team": "ERA Basketball Nymburk", "on_min": 351, "on_ortg": 145.6, "on_drtg": 100.8, "on_net": 44.8, "off_min": 318, "off_ortg": 127.6, "off_drtg": 106.0, "off_net": 21.6, "delta_net": 23.2}, {"first_name": "Ondřej", "family_name": "Hornický", "slug": "sluneta-usti-nad-labem-ondrej-hornicky", "season": "2025-26", "team": "SLUNETA  Ústí nad Labem", "on_min": 2, "on_ortg": 177.2, "on_drtg": 133.0, "on_net": 44.2, "off_min": 38, "off_ortg": 153.5, "off_drtg": 102.7, "off_net": 50.8, "delta_net": -6.6}, {"first_name": "Thomas", "family_name": "Stanko", "slug": "era-basketball-nymburk-thomas-stanko", "season": "2025-26", "team": "ERA Basketball Nymburk", "on_min": 14, "on_ortg": 144.2, "on_drtg": 100.9, "on_net": 43.3, "off_min": 63, "off_ortg": 123.3, "off_drtg": 100.7, "off_net": 22.6, "delta_net": 20.7}, {"first_name": "Vojtěch", "family_name": "Hruban", "slug": "era-basketball-nymburk-vojtech-hruban", "season": "2025-26", "team": "ERA Basketball Nymburk", "on_min": 442, "on_ortg": 139.7, "on_drtg": 98.6, "on_net": 41.1, "off_min": 583, "off_ortg": 131.2, "off_drtg": 103.4, "off_net": 27.8, "delta_net": 13.3}, {"first_name": "Jhamir", "family_name": "Brickus", "slug": "era-basketball-nymburk-jhamir-brickus", "season": "2025-26", "team": "ERA Basketball Nymburk", "on_min": 335, "on_ortg": 139.9, "on_drtg": 99.4, "on_net": 40.5, "off_min": 377, "off_ortg": 136.0, "off_drtg": 103.6, "off_net": 32.4, "delta_net": 8.1}, {"first_name": "František", "family_name": "Rylich", "slug": "era-basketball-nymburk-frantisek-rylich", "season": "2025-26", "team": "ERA Basketball Nymburk", "on_min": 519, "on_ortg": 139.5, "on_drtg": 101.4, "on_net": 38.1, "off_min": 546, "off_ortg": 131.5, "off_drtg": 102.9, "off_net": 28.6, "delta_net": 9.5}, {"first_name": "Matěj", "family_name": "Střelba", "slug": "sk-slavia-praha-matej-strelba", "season": "2025-26", "team": "SK Slavia Praha", "on_min": 1, "on_ortg": 200.0, "on_drtg": 163.9, "on_net": 36.1, "off_min": 39, "off_ortg": 124.5, "off_drtg": 100.0, "off_net": 24.5, "delta_net": 11.6}, {"first_name": "Ondřej", "family_name": "Pospíchal", "slug": "sk-slavia-praha-ondrej-pospichal", "season": "2025-26", "team": "SK Slavia Praha", "on_min": 1, "on_ortg": 200.0, "on_drtg": 163.9, "on_net": 36.1, "off_min": 39, "off_ortg": 124.5, "off_drtg": 100.0, "off_net": 24.5, "delta_net": 11.6}, {"first_name": "Jaquan", "family_name": "Lawrence", "slug": "era-basketball-nymburk-jaquan-lawrence", "season": "2025-26", "team": "ERA Basketball Nymburk", "on_min": 382, "on_ortg": 134.2, "on_drtg": 98.8, "on_net": 35.4, "off_min": 566, "off_ortg": 136.4, "off_drtg": 104.0, "off_net": 32.4, "delta_net": 3.0}, {"first_name": "Ondřej", "family_name": "Sehnal", "slug": "era-basketball-nymburk-ondrej-sehnal", "season": "2025-26", "team": "ERA Basketball Nymburk", "on_min": 457, "on_ortg": 138.2, "on_drtg": 106.8, "on_net": 31.4, "off_min": 411, "off_ortg": 133.0, "off_drtg": 103.8, "off_net": 29.2, "delta_net": 2.2}, {"first_name": "Matěj", "family_name": "Svoboda", "slug": "era-basketball-nymburk-matej-svoboda", "season": "2025-26", "team": "ERA Basketball Nymburk", "on_min": 486, "on_ortg": 132.7, "on_drtg": 101.5, "on_net": 31.2, "off_min": 501, "off_ortg": 137.6, "off_drtg": 102.0, "off_net": 35.6, "delta_net": -4.4}, {"first_name": "Jaromír", "family_name": "Bohačík", "slug": "era-basketball-nymburk-jaromir-bohacik", "season": "2025-26", "team": "ERA Basketball Nymburk", "on_min": 446, "on_ortg": 131.1, "on_drtg": 100.0, "on_net": 31.1, "off_min": 421, "off_ortg": 140.0, "off_drtg": 106.4, "off_net": 33.6, "delta_net": -2.5}, {"first_name": "Tomáš", "family_name": "Houzar", "slug": "pumpa-basket-brno-tomas-houzar", "season": "2025-26", "team": "PUMPA Basket Brno", "on_min": 12, "on_ortg": 112.6, "on_drtg": 82.3, "on_net": 30.3, "off_min": 68, "off_ortg": 90.0, "off_drtg": 108.8, "off_net": -18.8, "delta_net": 49.1}, {"first_name": "Sir Jabari", "family_name": "Rice", "slug": "era-basketball-nymburk-sir-jabari-rice", "season": "2025-26", "team": "ERA Basketball Nymburk", "on_min": 446, "on_ortg": 136.7, "on_drtg": 108.0, "on_net": 28.7, "off_min": 463, "off_ortg": 136.1, "off_drtg": 100.5, "off_net": 35.6, "delta_net": -6.9}, {"first_name": "Jacob Nicholas", "family_name": "Evans Iii", "slug": "bk-kvis-pardubice-jacob-nicholas-evans-iii", "season": "2025-26", "team": "BK KVIS Pardubice", "on_min": 142, "on_ortg": 124.2, "on_drtg": 96.5, "on_net": 27.7, "off_min": 213, "off_ortg": 130.1, "off_drtg": 111.2, "off_net": 18.9, "delta_net": 8.8}, {"first_name": "Martin", "family_name": "Kříž", "slug": "era-basketball-nymburk-martin-kriz", "season": "2025-26", "team": "ERA Basketball Nymburk", "on_min": 443, "on_ortg": 133.1, "on_drtg": 105.6, "on_net": 27.5, "off_min": 543, "off_ortg": 138.1, "off_drtg": 100.5, "off_net": 37.6, "delta_net": -10.1}, {"first_name": "Přemysl", "family_name": "Dubový", "slug": "bk-opava-premysl-dubovy", "season": "2025-26", "team": "BK Opava", "on_min": 29, "on_ortg": 122.8, "on_drtg": 97.8, "on_net": 25.0, "off_min": 128, "off_ortg": 141.4, "off_drtg": 113.8, "off_net": 27.6, "delta_net": -2.6}, {"first_name": "Wesley", "family_name": "Dreamer", "slug": "era-basketball-nymburk-wesley-dreamer", "season": "2025-26", "team": "ERA Basketball Nymburk", "on_min": 258, "on_ortg": 128.3, "on_drtg": 105.1, "on_net": 23.2, "off_min": 256, "off_ortg": 136.2, "off_drtg": 94.2, "off_net": 42.0, "delta_net": -18.8}, {"first_name": "Jakub", "family_name": "Chaloupka", "slug": "usk-praha-jakub-chaloupka", "season": "2025-26", "team": "USK Praha", "on_min": 15, "on_ortg": 145.1, "on_drtg": 122.7, "on_net": 22.4, "off_min": 64, "off_ortg": 138.0, "off_drtg": 116.8, "off_net": 21.2, "delta_net": 1.2}, {"first_name": "Jakub", "family_name": "Tůma", "slug": "bk-kvis-pardubice-jakub-tuma", "season": "2025-26", "team": "BK KVIS Pardubice", "on_min": 663, "on_ortg": 132.3, "on_drtg": 110.8, "on_net": 21.5, "off_min": 476, "off_ortg": 124.2, "off_drtg": 111.5, "off_net": 12.7, "delta_net": 8.8}, {"first_name": "Luboš", "family_name": "Kovář", "slug": "bk-kvis-pardubice-lubos-kovar", "season": "2025-26", "team": "BK KVIS Pardubice", "on_min": 783, "on_ortg": 130.6, "on_drtg": 109.2, "on_net": 21.4, "off_min": 356, "off_ortg": 125.1, "off_drtg": 115.3, "off_net": 9.8, "delta_net": 11.6}, {"first_name": "Ryan Everett", "family_name": "Moffatt", "slug": "bk-kvis-pardubice-ryan-everett-moffatt", "season": "2025-26", "team": "BK KVIS Pardubice", "on_min": 771, "on_ortg": 130.5, "on_drtg": 109.3, "on_net": 21.2, "off_min": 288, "off_ortg": 123.2, "off_drtg": 112.7, "off_net": 10.5, "delta_net": 10.7}, {"first_name": "Ross Anthony", "family_name": "Williams", "slug": "pumpa-basket-brno-ross-anthony-williams", "season": "2025-26", "team": "PUMPA Basket Brno", "on_min": 282, "on_ortg": 128.9, "on_drtg": 108.1, "on_net": 20.8, "off_min": 124, "off_ortg": 140.0, "off_drtg": 107.8, "off_net": 32.2, "delta_net": -11.4}, {"first_name": "Jamonda Roshawn", "family_name": "Bryant ", "slug": "bk-kvis-pardubice-jamonda-roshawn-bryant", "season": "2025-26", "team": "BK KVIS Pardubice", "on_min": 789, "on_ortg": 130.3, "on_drtg": 110.3, "on_net": 20.0, "off_min": 350, "off_ortg": 125.6, "off_drtg": 112.8, "off_net": 12.8, "delta_net": 7.2}, {"first_name": "Vojtěch", "family_name": "Synáček", "slug": "era-basketball-nymburk-vojtech-synacek", "season": "2025-26", "team": "ERA Basketball Nymburk", "on_min": 121, "on_ortg": 114.2, "on_drtg": 95.0, "on_net": 19.2, "off_min": 473, "off_ortg": 139.8, "off_drtg": 101.5, "off_net": 38.3, "delta_net": -19.1}, {"first_name": "Martin", "family_name": "Nábělek", "slug": "bk-kvis-pardubice-martin-nabelek", "season": "2025-26", "team": "BK KVIS Pardubice", "on_min": 207, "on_ortg": 126.7, "on_drtg": 107.6, "on_net": 19.1, "off_min": 704, "off_ortg": 129.8, "off_drtg": 113.3, "off_net": 16.5, "delta_net": 2.6}, {"first_name": "Zed Jackson", "family_name": "Key", "slug": "bk-kvis-pardubice-zed-jackson-key", "season": "2025-26", "team": "BK KVIS Pardubice", "on_min": 606, "on_ortg": 130.7, "on_drtg": 111.8, "on_net": 18.9, "off_min": 533, "off_ortg": 126.7, "off_drtg": 110.3, "off_net": 16.4, "delta_net": 2.5}, {"first_name": "J´d Derryus", "family_name": "Eatmon", "slug": "sluneta-usti-nad-labem-j-d-derryus-eatmon", "season": "2025-26", "team": "SLUNETA  Ústí nad Labem", "on_min": 77, "on_ortg": 126.2, "on_drtg": 107.7, "on_net": 18.5, "off_min": 238, "off_ortg": 116.7, "off_drtg": 123.7, "off_net": -7.0, "delta_net": 25.5}, {"first_name": "Maroš", "family_name": "Šimko", "slug": "pumpa-basket-brno-maros-simko", "season": "2025-26", "team": "PUMPA Basket Brno", "on_min": 29, "on_ortg": 134.7, "on_drtg": 116.3, "on_net": 18.4, "off_min": 128, "off_ortg": 119.8, "off_drtg": 109.0, "off_net": 10.8, "delta_net": 7.6}, {"first_name": "Posh", "family_name": "Alexander", "slug": "bk-armex-energy-decin-posh-alexander", "season": "2025-26", "team": "BK ARMEX ENERGY Děčín", "on_min": 431, "on_ortg": 129.8, "on_drtg": 112.1, "on_net": 17.7, "off_min": 242, "off_ortg": 113.0, "off_drtg": 117.7, "off_net": -4.7, "delta_net": 22.4}, {"first_name": "Hameir", "family_name": "Wright", "slug": "usk-praha-hameir-wright", "season": "2025-26", "team": "USK Praha", "on_min": 58, "on_ortg": 109.5, "on_drtg": 92.8, "on_net": 16.7, "off_min": 59, "off_ortg": 137.7, "off_drtg": 116.1, "off_net": 21.6, "delta_net": -4.9}, {"first_name": "David Emmanuel", "family_name": "Walker", "slug": "sk-slavia-praha-david-emmanuel-walker", "season": "2025-26", "team": "SK Slavia Praha", "on_min": 17, "on_ortg": 103.4, "on_drtg": 86.8, "on_net": 16.6, "off_min": 22, "off_ortg": 106.7, "off_drtg": 106.1, "off_net": 0.6, "delta_net": 16.0}, {"first_name": "David", "family_name": "Nejezchleb", "slug": "era-basketball-nymburk-david-nejezchleb", "season": "2025-26", "team": "ERA Basketball Nymburk", "on_min": 86, "on_ortg": 121.2, "on_drtg": 104.7, "on_net": 16.5, "off_min": 429, "off_ortg": 143.3, "off_drtg": 91.7, "off_net": 51.6, "delta_net": -35.1}, {"first_name": "Kryštof", "family_name": "Kavan", "slug": "bk-opava-krystof-kavan", "season": "2025-26", "team": "BK Opava", "on_min": 316, "on_ortg": 132.1, "on_drtg": 116.7, "on_net": 15.4, "off_min": 645, "off_ortg": 124.6, "off_drtg": 126.4, "off_net": -1.8, "delta_net": 17.2}, {"first_name": "Robert Lee", "family_name": "Bonham", "slug": "bk-kvis-pardubice-robert-lee-bonham", "season": "2025-26", "team": "BK KVIS Pardubice", "on_min": 735, "on_ortg": 128.7, "on_drtg": 113.9, "on_net": 14.8, "off_min": 365, "off_ortg": 127.5, "off_drtg": 107.2, "off_net": 20.3, "delta_net": -5.5}, {"first_name": "Keyshawn Maklik", "family_name": "Feazell", "slug": "era-basketball-nymburk-keyshawn-maklik-feazell", "season": "2025-26", "team": "ERA Basketball Nymburk", "on_min": 246, "on_ortg": 125.5, "on_drtg": 110.9, "on_net": 14.6, "off_min": 267, "off_ortg": 138.7, "off_drtg": 102.0, "off_net": 36.7, "delta_net": -22.1}, {"first_name": "Kamil", "family_name": "Švrdlík", "slug": "bk-kvis-pardubice-kamil-svrdlik", "season": "2025-26", "team": "BK KVIS Pardubice", "on_min": 442, "on_ortg": 125.8, "on_drtg": 111.7, "on_net": 14.1, "off_min": 697, "off_ortg": 130.8, "off_drtg": 110.7, "off_net": 20.1, "delta_net": -6.0}, {"first_name": "Josef", "family_name": "Potoček", "slug": "sluneta-usti-nad-labem-josef-potocek", "season": "2025-26", "team": "SLUNETA  Ústí nad Labem", "on_min": 519, "on_ortg": 123.0, "on_drtg": 112.3, "on_net": 10.7, "off_min": 572, "off_ortg": 118.7, "off_drtg": 122.6, "off_net": -3.9, "delta_net": 14.6}, {"first_name": "Vojtěch", "family_name": "Sýkora", "slug": "srsni-photomate-pisek-vojtech-sykora", "season": "2025-26", "team": "Sršni Photomate Písek", "on_min": 471, "on_ortg": 127.0, "on_drtg": 116.5, "on_net": 10.5, "off_min": 270, "off_ortg": 115.8, "off_drtg": 116.8, "off_net": -1.0, "delta_net": 11.5}, {"first_name": "Jan", "family_name": "Karlovský", "slug": "srsni-photomate-pisek-jan-karlovsky", "season": "2025-26", "team": "Sršni Photomate Písek", "on_min": 583, "on_ortg": 123.1, "on_drtg": 112.8, "on_net": 10.3, "off_min": 462, "off_ortg": 120.2, "off_drtg": 126.8, "off_net": -6.6, "delta_net": 16.9}, {"first_name": "Lloyd Alvin", "family_name": "Bryan Jr", "slug": "bk-armex-energy-decin-lloyd-alvin-bryan-jr", "season": "2025-26", "team": "BK ARMEX ENERGY Děčín", "on_min": 159, "on_ortg": 123.6, "on_drtg": 113.6, "on_net": 10.0, "off_min": 314, "off_ortg": 114.4, "off_drtg": 117.4, "off_net": -3.0, "delta_net": 13.0}, {"first_name": "Marek", "family_name": "Vyroubal", "slug": "bk-opava-marek-vyroubal", "season": "2025-26", "team": "BK Opava", "on_min": 490, "on_ortg": 127.1, "on_drtg": 118.0, "on_net": 9.1, "off_min": 430, "off_ortg": 121.6, "off_drtg": 122.2, "off_net": -0.6, "delta_net": 9.7}, {"first_name": "Jakub", "family_name": "Šurý", "slug": "srsni-photomate-pisek-jakub-sury", "season": "2025-26", "team": "Sršni Photomate Písek", "on_min": 226, "on_ortg": 129.1, "on_drtg": 120.8, "on_net": 8.3, "off_min": 280, "off_ortg": 113.8, "off_drtg": 119.1, "off_net": -5.3, "delta_net": 13.6}, {"first_name": "Tony", "family_name": "Perkins", "slug": "era-basketball-nymburk-tony-perkins", "season": "2025-26", "team": "ERA Basketball Nymburk", "on_min": 48, "on_ortg": 113.4, "on_drtg": 105.3, "on_net": 8.1, "off_min": 70, "off_ortg": 153.4, "off_drtg": 101.2, "off_net": 52.2, "delta_net": -44.1}, {"first_name": "Jakub", "family_name": "Zvolánek", "slug": "srsni-photomate-pisek-jakub-zvolanek", "season": "2025-26", "team": "Sršni Photomate Písek", "on_min": 278, "on_ortg": 120.3, "on_drtg": 112.7, "on_net": 7.6, "off_min": 689, "off_ortg": 121.7, "off_drtg": 123.3, "off_net": -1.6, "delta_net": 9.2}, {"first_name": "Viktor", "family_name": "Půlpán", "slug": "pumpa-basket-brno-viktor-pulpan", "season": "2025-26", "team": "PUMPA Basket Brno", "on_min": 432, "on_ortg": 120.7, "on_drtg": 113.8, "on_net": 6.9, "off_min": 364, "off_ortg": 120.3, "off_drtg": 119.8, "off_net": 0.5, "delta_net": 6.4}, {"first_name": "David", "family_name": "Motyčka", "slug": "bk-opava-david-motycka", "season": "2025-26", "team": "BK Opava", "on_min": 174, "on_ortg": 130.6, "on_drtg": 124.4, "on_net": 6.2, "off_min": 623, "off_ortg": 128.1, "off_drtg": 118.3, "off_net": 9.8, "delta_net": -3.6}, {"first_name": "Ladislav", "family_name": "Pecka", "slug": "sluneta-usti-nad-labem-ladislav-pecka", "season": "2025-26", "team": "SLUNETA  Ústí nad Labem", "on_min": 732, "on_ortg": 120.8, "on_drtg": 114.8, "on_net": 6.0, "off_min": 359, "off_ortg": 120.4, "off_drtg": 123.4, "off_net": -3.0, "delta_net": 9.0}, {"first_name": "Jacob Austin", "family_name": "Groves", "slug": "pumpa-basket-brno-jacob-austin-groves", "season": "2025-26", "team": "PUMPA Basket Brno", "on_min": 346, "on_ortg": 121.6, "on_drtg": 115.7, "on_net": 5.9, "off_min": 179, "off_ortg": 130.5, "off_drtg": 106.9, "off_net": 23.6, "delta_net": -17.7}, {"first_name": "Adam", "family_name": "Kejval", "slug": "pumpa-basket-brno-adam-kejval", "season": "2025-26", "team": "PUMPA Basket Brno", "on_min": 513, "on_ortg": 121.4, "on_drtg": 115.7, "on_net": 5.7, "off_min": 404, "off_ortg": 118.7, "off_drtg": 119.7, "off_net": -1.0, "delta_net": 6.7}, {"first_name": "Tomáš", "family_name": "Jansa", "slug": "pumpa-basket-brno-tomas-jansa", "season": "2025-26", "team": "PUMPA Basket Brno", "on_min": 233, "on_ortg": 126.8, "on_drtg": 121.3, "on_net": 5.5, "off_min": 643, "off_ortg": 114.7, "off_drtg": 114.4, "off_net": 0.3, "delta_net": 5.2}, {"first_name": "Petr", "family_name": "Šťovíček", "slug": "bk-kvis-pardubice-petr-stovicek", "season": "2025-26", "team": "BK KVIS Pardubice", "on_min": 31, "on_ortg": 122.9, "on_drtg": 117.8, "on_net": 5.1, "off_min": 288, "off_ortg": 136.4, "off_drtg": 106.1, "off_net": 30.3, "delta_net": -25.2}, {"first_name": "Jayhlon", "family_name": "Young", "slug": "sluneta-usti-nad-labem-jayhlon-young", "season": "2025-26", "team": "SLUNETA  Ústí nad Labem", "on_min": 585, "on_ortg": 122.1, "on_drtg": 117.0, "on_net": 5.1, "off_min": 506, "off_ortg": 119.0, "off_drtg": 118.4, "off_net": 0.6, "delta_net": 4.5}, {"first_name": "Martin", "family_name": "Svoboda", "slug": "srsni-photomate-pisek-martin-svoboda", "season": "2025-26", "team": "Sršni Photomate Písek", "on_min": 791, "on_ortg": 126.5, "on_drtg": 121.5, "on_net": 5.0, "off_min": 254, "off_ortg": 110.2, "off_drtg": 117.0, "off_net": -6.8, "delta_net": 11.8}, {"first_name": "Nicholas", "family_name": "Johnson", "slug": "sluneta-usti-nad-labem-nicholas-johnson", "season": "2025-26", "team": "SLUNETA  Ústí nad Labem", "on_min": 761, "on_ortg": 120.5, "on_drtg": 115.5, "on_net": 5.0, "off_min": 330, "off_ortg": 121.1, "off_drtg": 122.7, "off_net": -1.6, "delta_net": 6.6}, {"first_name": "Jan", "family_name": "Švandrlík", "slug": "bk-opava-jan-svandrlik", "season": "2025-26", "team": "BK Opava", "on_min": 576, "on_ortg": 129.4, "on_drtg": 124.9, "on_net": 4.5, "off_min": 542, "off_ortg": 119.6, "off_drtg": 117.8, "off_net": 1.8, "delta_net": 2.7}, {"first_name": "Vojtěch", "family_name": "Synáček", "slug": "bk-gapa-hradec-kralove-vojtech-synacek", "season": "2025-26", "team": "BK GAPA Hradec Králové", "on_min": 157, "on_ortg": 119.1, "on_drtg": 114.6, "on_net": 4.5, "off_min": 78, "off_ortg": 94.8, "off_drtg": 122.8, "off_net": -28.0, "delta_net": 32.5}, {"first_name": "Milan Tomáš", "family_name": "Stráněl", "slug": "pumpa-basket-brno-milan-tomas-stranel", "season": "2025-26", "team": "PUMPA Basket Brno", "on_min": 425, "on_ortg": 123.8, "on_drtg": 119.6, "on_net": 4.2, "off_min": 608, "off_ortg": 116.2, "off_drtg": 117.2, "off_net": -1.0, "delta_net": 5.2}, {"first_name": "František", "family_name": "Váňa", "slug": "bk-opava-frantisek-vana", "season": "2025-26", "team": "BK Opava", "on_min": 89, "on_ortg": 120.0, "on_drtg": 115.8, "on_net": 4.2, "off_min": 269, "off_ortg": 120.7, "off_drtg": 121.6, "off_net": -0.9, "delta_net": 5.1}, {"first_name": "Petr", "family_name": "Šlechta", "slug": "srsni-photomate-pisek-petr-slechta", "season": "2025-26", "team": "Sršni Photomate Písek", "on_min": 457, "on_ortg": 129.3, "on_drtg": 125.2, "on_net": 4.1, "off_min": 439, "off_ortg": 115.1, "off_drtg": 116.0, "off_net": -0.9, "delta_net": 5.0}, {"first_name": "František", "family_name": "Fuxa", "slug": "usk-praha-frantisek-fuxa", "season": "2025-26", "team": "USK Praha", "on_min": 283, "on_ortg": 122.0, "on_drtg": 118.0, "on_net": 4.0, "off_min": 733, "off_ortg": 111.9, "off_drtg": 129.6, "off_net": -17.7, "delta_net": 21.7}, {"first_name": "Radovan", "family_name": "Kouřil", "slug": "bk-opava-radovan-kouril", "season": "2025-26", "team": "BK Opava", "on_min": 463, "on_ortg": 124.4, "on_drtg": 120.9, "on_net": 3.5, "off_min": 324, "off_ortg": 130.8, "off_drtg": 123.8, "off_net": 7.0, "delta_net": -3.5}, {"first_name": "Vojtěch", "family_name": "Zeithammer", "slug": "sk-slavia-praha-vojtech-zeithammer", "season": "2025-26", "team": "SK Slavia Praha", "on_min": 30, "on_ortg": 139.1, "on_drtg": 135.8, "on_net": 3.3, "off_min": 167, "off_ortg": 118.7, "off_drtg": 120.4, "off_net": -1.7, "delta_net": 5.0}, {"first_name": "Filip", "family_name": "Zbránek", "slug": "bk-opava-filip-zbranek", "season": "2025-26", "team": "BK Opava", "on_min": 236, "on_ortg": 119.3, "on_drtg": 116.1, "on_net": 3.2, "off_min": 455, "off_ortg": 120.9, "off_drtg": 125.4, "off_net": -4.5, "delta_net": 7.7}, {"first_name": "Dashawn Calvin", "family_name": "Davis", "slug": "bk-armex-energy-decin-dashawn-calvin-davis", "season": "2025-26", "team": "BK ARMEX ENERGY Děčín", "on_min": 690, "on_ortg": 119.9, "on_drtg": 116.8, "on_net": 3.1, "off_min": 299, "off_ortg": 112.9, "off_drtg": 118.2, "off_net": -5.3, "delta_net": 8.4}, {"first_name": "Kevin Chukwuemeka", "family_name": "Kalu", "slug": "pumpa-basket-brno-kevin-chukwuemeka-kalu", "season": "2025-26", "team": "PUMPA Basket Brno", "on_min": 384, "on_ortg": 119.0, "on_drtg": 115.9, "on_net": 3.1, "off_min": 376, "off_ortg": 120.3, "off_drtg": 110.4, "off_net": 9.9, "delta_net": -6.8}, {"first_name": "Isaac", "family_name": "Davidson", "slug": "sluneta-usti-nad-labem-isaac-davidson", "season": "2025-26", "team": "SLUNETA  Ústí nad Labem", "on_min": 401, "on_ortg": 121.3, "on_drtg": 118.3, "on_net": 3.0, "off_min": 191, "off_ortg": 124.2, "off_drtg": 106.6, "off_net": 17.6, "delta_net": -14.6}, {"first_name": "Oliver", "family_name": "Žižka", "slug": "bk-armex-energy-decin-oliver-zizka", "season": "2025-26", "team": "BK ARMEX ENERGY Děčín", "on_min": 42, "on_ortg": 115.9, "on_drtg": 113.1, "on_net": 2.8, "off_min": 393, "off_ortg": 123.8, "off_drtg": 113.3, "off_net": 10.5, "delta_net": -7.7}, {"first_name": "Adam", "family_name": "Lukeš", "slug": "bk-kvis-pardubice-adam-lukes", "season": "2025-26", "team": "BK KVIS Pardubice", "on_min": 434, "on_ortg": 120.4, "on_drtg": 117.7, "on_net": 2.7, "off_min": 478, "off_ortg": 128.8, "off_drtg": 106.9, "off_net": 21.9, "delta_net": -19.2}, {"first_name": "Isaiah John", "family_name": "Gray", "slug": "bk-opava-isaiah-john-gray", "season": "2025-26", "team": "BK Opava", "on_min": 138, "on_ortg": 123.3, "on_drtg": 120.6, "on_net": 2.7, "off_min": 74, "off_ortg": 116.2, "off_drtg": 114.7, "off_net": 1.5, "delta_net": 1.2}, {"first_name": "Kevin", "family_name": "Týml", "slug": "srsni-photomate-pisek-kevin-tyml", "season": "2025-26", "team": "Sršni Photomate Písek", "on_min": 721, "on_ortg": 121.9, "on_drtg": 119.3, "on_net": 2.6, "off_min": 363, "off_ortg": 122.0, "off_drtg": 120.7, "off_net": 1.3, "delta_net": 1.3}, {"first_name": "Maksim", "family_name": "Šturanović", "slug": "bk-armex-energy-decin-maksim-sturanovic", "season": "2025-26", "team": "BK ARMEX ENERGY Děčín", "on_min": 469, "on_ortg": 119.0, "on_drtg": 116.7, "on_net": 2.3, "off_min": 676, "off_ortg": 116.5, "off_drtg": 119.6, "off_net": -3.1, "delta_net": 5.4}, {"first_name": "Clevon", "family_name": "Brown Jr", "slug": "bk-opava-clevon-brown-jr", "season": "2025-26", "team": "BK Opava", "on_min": 743, "on_ortg": 123.2, "on_drtg": 121.2, "on_net": 2.0, "off_min": 375, "off_ortg": 127.6, "off_drtg": 121.7, "off_net": 5.9, "delta_net": -3.9}, {"first_name": "Jakub", "family_name": "Slavík", "slug": "bk-opava-jakub-slavik", "season": "2025-26", "team": "BK Opava", "on_min": 448, "on_ortg": 121.7, "on_drtg": 119.9, "on_net": 1.8, "off_min": 508, "off_ortg": 127.1, "off_drtg": 123.7, "off_net": 3.4, "delta_net": -1.6}, {"first_name": "Petr", "family_name": "Křivánek", "slug": "pumpa-basket-brno-petr-krivanek", "season": "2025-26", "team": "PUMPA Basket Brno", "on_min": 527, "on_ortg": 118.0, "on_drtg": 116.3, "on_net": 1.7, "off_min": 432, "off_ortg": 124.4, "off_drtg": 117.5, "off_net": 6.9, "delta_net": -5.2}, {"first_name": "Matěj", "family_name": "Rychtecký", "slug": "pumpa-basket-brno-matej-rychtecky", "season": "2025-26", "team": "PUMPA Basket Brno", "on_min": 393, "on_ortg": 117.4, "on_drtg": 116.1, "on_net": 1.3, "off_min": 523, "off_ortg": 123.0, "off_drtg": 121.6, "off_net": 1.4, "delta_net": -0.1}, {"first_name": "Jonáš", "family_name": "Musil", "slug": "pumpa-basket-brno-jonas-musil", "season": "2025-26", "team": "PUMPA Basket Brno", "on_min": 135, "on_ortg": 117.8, "on_drtg": 116.5, "on_net": 1.3, "off_min": 489, "off_ortg": 121.4, "off_drtg": 115.7, "off_net": 5.7, "delta_net": -4.4}, {"first_name": "Josef", "family_name": "Gabriel", "slug": "bk-armex-energy-decin-josef-gabriel", "season": "2025-26", "team": "BK ARMEX ENERGY Děčín", "on_min": 86, "on_ortg": 129.1, "on_drtg": 128.0, "on_net": 1.1, "off_min": 705, "off_ortg": 115.8, "off_drtg": 119.6, "off_net": -3.8, "delta_net": 4.9}, {"first_name": "David", "family_name": "Žikla", "slug": "sluneta-usti-nad-labem-david-zikla", "season": "2025-26", "team": "SLUNETA  Ústí nad Labem", "on_min": 332, "on_ortg": 118.2, "on_drtg": 117.1, "on_net": 1.1, "off_min": 680, "off_ortg": 119.8, "off_drtg": 118.5, "off_net": 1.3, "delta_net": -0.2}, {"first_name": "Tomáš", "family_name": "Vyoral", "slug": "sluneta-usti-nad-labem-tomas-vyoral", "season": "2025-26", "team": "SLUNETA  Ústí nad Labem", "on_min": 732, "on_ortg": 121.4, "on_drtg": 120.9, "on_net": 0.5, "off_min": 280, "off_ortg": 122.7, "off_drtg": 110.8, "off_net": 11.9, "delta_net": -11.4}, {"first_name": "Šimon", "family_name": "Puršl", "slug": "bk-opava-simon-pursl", "season": "2025-26", "team": "BK Opava", "on_min": 615, "on_ortg": 121.8, "on_drtg": 121.7, "on_net": 0.1, "off_min": 423, "off_ortg": 128.8, "off_drtg": 123.1, "off_net": 5.7, "delta_net": -5.6}, {"first_name": "Jakub", "family_name": "Šiřina", "slug": "bk-opava-jakub-sirina", "season": "2025-26", "team": "BK Opava", "on_min": 548, "on_ortg": 124.1, "on_drtg": 124.1, "on_net": 0.0, "off_min": 499, "off_ortg": 126.1, "off_drtg": 116.6, "off_net": 9.5, "delta_net": -9.5}, {"first_name": "Jalen Terence", "family_name": "Montgomery", "slug": "usk-praha-jalen-terence-montgomery", "season": "2025-26", "team": "USK Praha", "on_min": 660, "on_ortg": 120.7, "on_drtg": 120.7, "on_net": 0.0, "off_min": 249, "off_ortg": 113.9, "off_drtg": 124.8, "off_net": -10.9, "delta_net": 10.9}, {"first_name": "Viktor", "family_name": "Ivánek", "slug": "pumpa-basket-brno-viktor-ivanek", "season": "2025-26", "team": "PUMPA Basket Brno", "on_min": 44, "on_ortg": 115.5, "on_drtg": 115.7, "on_net": -0.2, "off_min": 265, "off_ortg": 117.3, "off_drtg": 128.8, "off_net": -11.5, "delta_net": 11.3}, {"first_name": "Michal", "family_name": "Grill", "slug": "bk-armex-energy-decin-michal-grill", "season": "2025-26", "team": "BK ARMEX ENERGY Děčín", "on_min": 84, "on_ortg": 105.8, "on_drtg": 106.4, "on_net": -0.6, "off_min": 270, "off_ortg": 121.2, "off_drtg": 121.1, "off_net": 0.1, "delta_net": -0.7}, {"first_name": "Filip", "family_name": "Kroutil", "slug": "bk-armex-energy-decin-filip-kroutil", "season": "2025-26", "team": "BK ARMEX ENERGY Děčín", "on_min": 669, "on_ortg": 117.7, "on_drtg": 118.4, "on_net": -0.7, "off_min": 476, "off_ortg": 117.3, "off_drtg": 118.5, "off_net": -1.2, "delta_net": 0.5}, {"first_name": "Adam", "family_name": "Pecháček", "slug": "sluneta-usti-nad-labem-adam-pechacek", "season": "2025-26", "team": "SLUNETA  Ústí nad Labem", "on_min": 598, "on_ortg": 117.2, "on_drtg": 118.0, "on_net": -0.8, "off_min": 493, "off_ortg": 125.1, "off_drtg": 117.2, "off_net": 7.9, "delta_net": -8.7}, {"first_name": "Josef", "family_name": "Svoboda", "slug": "srsni-photomate-pisek-josef-svoboda", "season": "2025-26", "team": "Sršni Photomate Písek", "on_min": 525, "on_ortg": 118.3, "on_drtg": 119.2, "on_net": -0.9, "off_min": 559, "off_ortg": 125.4, "off_drtg": 120.3, "off_net": 5.1, "delta_net": -6.0}, {"first_name": "Wesley Lavon", "family_name": "Person Jr", "slug": "bk-opava-wesley-lavon-person-jr", "season": "2025-26", "team": "BK Opava", "on_min": 665, "on_ortg": 123.1, "on_drtg": 124.1, "on_net": -1.0, "off_min": 296, "off_ortg": 127.7, "off_drtg": 117.8, "off_net": 9.9, "delta_net": -10.9}, {"first_name": "Petr", "family_name": "Macháč", "slug": "bk-armex-energy-decin-petr-machac", "season": "2025-26", "team": "BK ARMEX ENERGY Děčín", "on_min": 70, "on_ortg": 112.8, "on_drtg": 114.1, "on_net": -1.3, "off_min": 244, "off_ortg": 114.9, "off_drtg": 123.0, "off_net": -8.1, "delta_net": 6.8}, {"first_name": "Jan", "family_name": "Štěrba", "slug": "bk-armex-energy-decin-jan-sterba", "season": "2025-26", "team": "BK ARMEX ENERGY Děčín", "on_min": 690, "on_ortg": 119.4, "on_drtg": 120.8, "on_net": -1.4, "off_min": 455, "off_ortg": 114.7, "off_drtg": 114.8, "off_net": -0.1, "delta_net": -1.3}, {"first_name": "František", "family_name": "Suchánek", "slug": "srsni-photomate-pisek-frantisek-suchanek", "season": "2025-26", "team": "Sršni Photomate Písek", "on_min": 107, "on_ortg": 111.0, "on_drtg": 112.6, "on_net": -1.6, "off_min": 388, "off_ortg": 118.8, "off_drtg": 119.1, "off_net": -0.3, "delta_net": -1.3}, {"first_name": "Tadeáš", "family_name": "Slowiak", "slug": "bk-armex-energy-decin-tadeas-slowiak", "season": "2025-26", "team": "BK ARMEX ENERGY Děčín", "on_min": 204, "on_ortg": 118.0, "on_drtg": 120.2, "on_net": -2.2, "off_min": 189, "off_ortg": 113.1, "off_drtg": 114.1, "off_net": -1.0, "delta_net": -1.2}, {"first_name": "Radek", "family_name": "Farský", "slug": "pumpa-basket-brno-radek-farsky", "season": "2025-26", "team": "PUMPA Basket Brno", "on_min": 476, "on_ortg": 118.3, "on_drtg": 120.5, "on_net": -2.2, "off_min": 539, "off_ortg": 119.5, "off_drtg": 118.8, "off_net": 0.7, "delta_net": -2.9}, {"first_name": "Jaden Dewar", "family_name": "Edwards", "slug": "bk-armex-energy-decin-jaden-dewar-edwards", "season": "2025-26", "team": "BK ARMEX ENERGY Děčín", "on_min": 717, "on_ortg": 115.5, "on_drtg": 118.0, "on_net": -2.5, "off_min": 428, "off_ortg": 120.9, "off_drtg": 119.0, "off_net": 1.9, "delta_net": -4.4}, {"first_name": "Filip", "family_name": "Kábrt", "slug": "sluneta-usti-nad-labem-filip-kabrt", "season": "2025-26", "team": "SLUNETA  Ústí nad Labem", "on_min": 459, "on_ortg": 120.6, "on_drtg": 123.1, "on_net": -2.5, "off_min": 632, "off_ortg": 120.8, "off_drtg": 113.7, "off_net": 7.1, "delta_net": -9.6}, {"first_name": "Michal", "family_name": "Kozák", "slug": "srsni-photomate-pisek-michal-kozak", "season": "2025-26", "team": "Sršni Photomate Písek", "on_min": 482, "on_ortg": 120.2, "on_drtg": 122.8, "on_net": -2.6, "off_min": 602, "off_ortg": 123.2, "off_drtg": 117.5, "off_net": 5.7, "delta_net": -8.3}, {"first_name": "Samuel Dennis", "family_name": "Godwin", "slug": "nh-ostrava-samuel-dennis-godwin", "season": "2025-26", "team": "NH Ostrava", "on_min": 319, "on_ortg": 125.8, "on_drtg": 129.2, "on_net": -3.4, "off_min": 439, "off_ortg": 117.0, "off_drtg": 127.2, "off_net": -10.2, "delta_net": 6.8}, {"first_name": "Tomáš", "family_name": "Pomikálek", "slug": "bk-armex-energy-decin-tomas-pomikalek", "season": "2025-26", "team": "BK ARMEX ENERGY Děčín", "on_min": 646, "on_ortg": 114.7, "on_drtg": 118.3, "on_net": -3.6, "off_min": 460, "off_ortg": 124.2, "off_drtg": 116.7, "off_net": 7.5, "delta_net": -11.1}, {"first_name": "Marek", "family_name": "Simonides", "slug": "bk-kvis-pardubice-marek-simonides", "season": "2025-26", "team": "BK KVIS Pardubice", "on_min": 53, "on_ortg": 119.6, "on_drtg": 123.4, "on_net": -3.8, "off_min": 386, "off_ortg": 127.4, "off_drtg": 108.5, "off_net": 18.9, "delta_net": -22.7}, {"first_name": "Terry", "family_name": "Henderson Jr.", "slug": "usk-praha-terry-henderson-jr", "season": "2025-26", "team": "USK Praha", "on_min": 607, "on_ortg": 120.0, "on_drtg": 123.8, "on_net": -3.8, "off_min": 184, "off_ortg": 121.0, "off_drtg": 117.0, "off_net": 4.0, "delta_net": -7.8}, {"first_name": "Petr", "family_name": "Krupka", "slug": "sluneta-usti-nad-labem-petr-krupka", "season": "2025-26", "team": "SLUNETA  Ústí nad Labem", "on_min": 66, "on_ortg": 131.9, "on_drtg": 135.9, "on_net": -4.0, "off_min": 408, "off_ortg": 119.6, "off_drtg": 110.5, "off_net": 9.1, "delta_net": -13.1}, {"first_name": "Ondřej", "family_name": "Šiška", "slug": "bk-olomoucko-ondrej-siska", "season": "2025-26", "team": "BK Olomoucko", "on_min": 626, "on_ortg": 116.4, "on_drtg": 120.5, "on_net": -4.1, "off_min": 405, "off_ortg": 107.1, "off_drtg": 121.6, "off_net": -14.5, "delta_net": 10.4}, {"first_name": "Michal", "family_name": "Svoboda", "slug": "nh-ostrava-michal-svoboda", "season": "2025-26", "team": "NH Ostrava", "on_min": 657, "on_ortg": 119.4, "on_drtg": 123.5, "on_net": -4.1, "off_min": 307, "off_ortg": 112.2, "off_drtg": 130.7, "off_net": -18.5, "delta_net": 14.4}, {"first_name": "Kimani", "family_name": "Lawrence", "slug": "sluneta-usti-nad-labem-kimani-lawrence", "season": "2025-26", "team": "SLUNETA  Ústí nad Labem", "on_min": 85, "on_ortg": 123.6, "on_drtg": 127.7, "on_net": -4.1, "off_min": 73, "off_ortg": 106.2, "off_drtg": 100.8, "off_net": 5.4, "delta_net": -9.5}, {"first_name": "Johan", "family_name": "Haiblík", "slug": "srsni-photomate-pisek-johan-haiblik", "season": "2025-26", "team": "Sršni Photomate Písek", "on_min": 283, "on_ortg": 113.6, "on_drtg": 117.9, "on_net": -4.3, "off_min": 724, "off_ortg": 123.6, "off_drtg": 120.9, "off_net": 2.7, "delta_net": -7.0}, {"first_name": "Luděk", "family_name": "Jurečka", "slug": "bk-opava-ludek-jurecka", "season": "2025-26", "team": "BK Opava", "on_min": 48, "on_ortg": 129.0, "on_drtg": 133.3, "on_net": -4.3, "off_min": 186, "off_ortg": 120.9, "off_drtg": 108.9, "off_net": 12.0, "delta_net": -16.3}, {"first_name": "Meschak Wandja", "family_name": "Lufile", "slug": "sk-slavia-praha-meschak-wandja-lufile", "season": "2025-26", "team": "SK Slavia Praha", "on_min": 266, "on_ortg": 115.4, "on_drtg": 119.7, "on_net": -4.3, "off_min": 329, "off_ortg": 118.3, "off_drtg": 121.9, "off_net": -3.6, "delta_net": -0.7}, {"first_name": "Ryker Broden", "family_name": "Cisarik", "slug": "pumpa-basket-brno-ryker-broden-cisarik", "season": "2025-26", "team": "PUMPA Basket Brno", "on_min": 80, "on_ortg": 111.8, "on_drtg": 116.2, "on_net": -4.4, "off_min": 37, "off_ortg": 108.1, "off_drtg": 147.9, "off_net": -39.8, "delta_net": 35.4}, {"first_name": "Tomáš", "family_name": "Palas", "slug": "usk-praha-tomas-palas", "season": "2025-26", "team": "USK Praha", "on_min": 54, "on_ortg": 122.3, "on_drtg": 127.3, "on_net": -5.0, "off_min": 408, "off_ortg": 112.8, "off_drtg": 132.1, "off_net": -19.3, "delta_net": 14.3}, {"first_name": "Lukáš", "family_name": "Palyza", "slug": "nh-ostrava-lukas-palyza", "season": "2025-26", "team": "NH Ostrava", "on_min": 641, "on_ortg": 120.1, "on_drtg": 125.3, "on_net": -5.2, "off_min": 513, "off_ortg": 113.7, "off_drtg": 125.5, "off_net": -11.8, "delta_net": 6.6}, {"first_name": "Elias ", "family_name": "Cato", "slug": "nh-ostrava-elias-cato", "season": "2025-26", "team": "NH Ostrava", "on_min": 376, "on_ortg": 115.8, "on_drtg": 121.5, "on_net": -5.7, "off_min": 422, "off_ortg": 124.2, "off_drtg": 130.8, "off_net": -6.6, "delta_net": 0.9}, {"first_name": "Šimon", "family_name": "Svoboda", "slug": "pumpa-basket-brno-simon-svoboda", "season": "2025-26", "team": "PUMPA Basket Brno", "on_min": 585, "on_ortg": 113.7, "on_drtg": 119.6, "on_net": -5.9, "off_min": 450, "off_ortg": 125.2, "off_drtg": 117.1, "off_net": 8.1, "delta_net": -14.0}, {"first_name": "Lynn Terence", "family_name": "Greer", "slug": "nh-ostrava-lynn-terence-greer", "season": "2025-26", "team": "NH Ostrava", "on_min": 679, "on_ortg": 117.9, "on_drtg": 124.1, "on_net": -6.2, "off_min": 395, "off_ortg": 117.6, "off_drtg": 126.6, "off_net": -9.0, "delta_net": 2.8}, {"first_name": "Mikuláš", "family_name": "Čank", "slug": "nh-ostrava-mikulas-cank", "season": "2025-26", "team": "NH Ostrava", "on_min": 583, "on_ortg": 115.2, "on_drtg": 121.5, "on_net": -6.3, "off_min": 492, "off_ortg": 120.0, "off_drtg": 127.5, "off_net": -7.5, "delta_net": 1.2}, {"first_name": "Kyler", "family_name": "Filewich", "slug": "bk-olomoucko-kyler-filewich", "season": "2025-26", "team": "BK Olomoucko", "on_min": 773, "on_ortg": 113.3, "on_drtg": 119.8, "on_net": -6.5, "off_min": 298, "off_ortg": 102.7, "off_drtg": 133.5, "off_net": -30.8, "delta_net": 24.3}, {"first_name": "Shamarkus", "family_name": "Kennedy", "slug": "sluneta-usti-nad-labem-shamarkus-kennedy", "season": "2025-26", "team": "SLUNETA  Ústí nad Labem", "on_min": 65, "on_ortg": 108.7, "on_drtg": 115.2, "on_net": -6.5, "off_min": 119, "off_ortg": 121.2, "off_drtg": 120.8, "off_net": 0.4, "delta_net": -6.9}, {"first_name": "Jan", "family_name": "Matušík", "slug": "sk-slavia-praha-jan-matusik", "season": "2025-26", "team": "SK Slavia Praha", "on_min": 527, "on_ortg": 121.9, "on_drtg": 129.0, "on_net": -7.1, "off_min": 524, "off_ortg": 106.5, "off_drtg": 125.9, "off_net": -19.4, "delta_net": 12.3}, {"first_name": "Cortesao Joao", "family_name": "Eduardo", "slug": "usk-praha-cortesao-joao-eduardo", "season": "2025-26", "team": "USK Praha", "on_min": 398, "on_ortg": 117.7, "on_drtg": 124.9, "on_net": -7.2, "off_min": 499, "off_ortg": 115.4, "off_drtg": 124.2, "off_net": -8.8, "delta_net": 1.6}, {"first_name": "Kobe", "family_name": "Elvis", "slug": "bk-olomoucko-kobe-elvis", "season": "2025-26", "team": "BK Olomoucko", "on_min": 607, "on_ortg": 114.5, "on_drtg": 122.7, "on_net": -8.2, "off_min": 227, "off_ortg": 104.4, "off_drtg": 126.1, "off_net": -21.7, "delta_net": 13.5}, {"first_name": "Pavel", "family_name": "Kaštil", "slug": "bk-opava-pavel-kastil", "season": "2025-26", "team": "BK Opava", "on_min": 5, "on_ortg": 129.2, "on_drtg": 137.5, "on_net": -8.3, "off_min": 113, "off_ortg": 145.3, "off_drtg": 117.3, "off_net": 28.0, "delta_net": -36.3}, {"first_name": "Keenon", "family_name": "Cole", "slug": "nh-ostrava-keenon-cole", "season": "2025-26", "team": "NH Ostrava", "on_min": 641, "on_ortg": 118.6, "on_drtg": 127.1, "on_net": -8.5, "off_min": 475, "off_ortg": 115.1, "off_drtg": 121.5, "off_net": -6.4, "delta_net": -2.1}, {"first_name": "Radovan", "family_name": "Mrázek", "slug": "sk-slavia-praha-radovan-mrazek", "season": "2025-26", "team": "SK Slavia Praha", "on_min": 550, "on_ortg": 116.9, "on_drtg": 125.8, "on_net": -8.9, "off_min": 422, "off_ortg": 112.6, "off_drtg": 127.5, "off_net": -14.9, "delta_net": 6.0}, {"first_name": "Tomáš", "family_name": "Merta", "slug": "bk-gapa-hradec-kralove-tomas-merta", "season": "2025-26", "team": "BK GAPA Hradec Králové", "on_min": 506, "on_ortg": 112.6, "on_drtg": 121.6, "on_net": -9.0, "off_min": 552, "off_ortg": 106.0, "off_drtg": 130.7, "off_net": -24.7, "delta_net": 15.7}, {"first_name": "Dalibor", "family_name": "Vlk", "slug": "usk-praha-dalibor-vlk", "season": "2025-26", "team": "USK Praha", "on_min": 655, "on_ortg": 118.1, "on_drtg": 127.4, "on_net": -9.3, "off_min": 479, "off_ortg": 110.7, "off_drtg": 121.9, "off_net": -11.2, "delta_net": 1.9}, {"first_name": "Petr", "family_name": "Macháč", "slug": "sk-slavia-praha-petr-machac", "season": "2025-26", "team": "SK Slavia Praha", "on_min": 353, "on_ortg": 113.2, "on_drtg": 122.5, "on_net": -9.3, "off_min": 441, "off_ortg": 118.4, "off_drtg": 129.1, "off_net": -10.7, "delta_net": 1.4}, {"first_name": "Matěj", "family_name": "Snopek", "slug": "nh-ostrava-matej-snopek", "season": "2025-26", "team": "NH Ostrava", "on_min": 237, "on_ortg": 118.2, "on_drtg": 127.5, "on_net": -9.3, "off_min": 720, "off_ortg": 117.7, "off_drtg": 125.8, "off_net": -8.1, "delta_net": -1.2}, {"first_name": "Rubin Patrick", "family_name": "Jones", "slug": "sk-slavia-praha-rubin-patrick-jones", "season": "2025-26", "team": "SK Slavia Praha", "on_min": 807, "on_ortg": 115.6, "on_drtg": 125.2, "on_net": -9.6, "off_min": 206, "off_ortg": 113.3, "off_drtg": 137.9, "off_net": -24.6, "delta_net": 15.0}, {"first_name": "Filip", "family_name": "Horváth", "slug": "bk-kvis-pardubice-filip-horvath", "season": "2025-26", "team": "BK KVIS Pardubice", "on_min": 7, "on_ortg": 98.5, "on_drtg": 108.5, "on_net": -10.0, "off_min": 113, "off_ortg": 127.9, "off_drtg": 109.0, "off_net": 18.9, "delta_net": -28.9}, {"first_name": "Marek", "family_name": "Houška", "slug": "bk-armex-energy-decin-marek-houska", "season": "2025-26", "team": "BK ARMEX ENERGY Děčín", "on_min": 68, "on_ortg": 108.4, "on_drtg": 118.5, "on_net": -10.1, "off_min": 248, "off_ortg": 124.2, "off_drtg": 114.7, "off_net": 9.5, "delta_net": -19.6}, {"first_name": "Adam", "family_name": "Číž", "slug": "nh-ostrava-adam-ciz", "season": "2025-26", "team": "NH Ostrava", "on_min": 747, "on_ortg": 117.6, "on_drtg": 128.0, "on_net": -10.4, "off_min": 367, "off_ortg": 117.8, "off_drtg": 120.4, "off_net": -2.6, "delta_net": -7.8}, {"first_name": "Dominik", "family_name": "Heinzl", "slug": "nh-ostrava-dominik-heinzl", "season": "2025-26", "team": "NH Ostrava", "on_min": 490, "on_ortg": 111.5, "on_drtg": 122.0, "on_net": -10.5, "off_min": 624, "off_ortg": 124.1, "off_drtg": 127.8, "off_net": -3.7, "delta_net": -6.8}, {"first_name": "Jaren Jamir", "family_name": "Holmes", "slug": "bk-olomoucko-jaren-jamir-holmes", "season": "2025-26", "team": "BK Olomoucko", "on_min": 550, "on_ortg": 109.7, "on_drtg": 120.7, "on_net": -11.0, "off_min": 166, "off_ortg": 114.9, "off_drtg": 139.2, "off_net": -24.3, "delta_net": 13.3}, {"first_name": "Lassi Paavo Verner", "family_name": "Nikkarinen", "slug": "bk-gapa-hradec-kralove-lassi-paavo-verner-nikkarinen", "season": "2025-26", "team": "BK GAPA Hradec Králové", "on_min": 415, "on_ortg": 113.1, "on_drtg": 124.2, "on_net": -11.1, "off_min": 132, "off_ortg": 121.5, "off_drtg": 122.6, "off_net": -1.1, "delta_net": -10.0}, {"first_name": "Matěj", "family_name": "Dáňa", "slug": "sk-slavia-praha-matej-dana", "season": "2025-26", "team": "SK Slavia Praha", "on_min": 587, "on_ortg": 116.5, "on_drtg": 127.8, "on_net": -11.3, "off_min": 344, "off_ortg": 109.8, "off_drtg": 128.2, "off_net": -18.4, "delta_net": 7.1}, {"first_name": "David", "family_name": "Jelínek", "slug": "pumpa-basket-brno-david-jelinek", "season": "2025-26", "team": "PUMPA Basket Brno", "on_min": 416, "on_ortg": 118.0, "on_drtg": 129.4, "on_net": -11.4, "off_min": 132, "off_ortg": 104.8, "off_drtg": 104.6, "off_net": 0.2, "delta_net": -11.6}, {"first_name": "Tomáš", "family_name": "Dvořák", "slug": "bk-gapa-hradec-kralove-tomas-dvorak", "season": "2025-26", "team": "BK GAPA Hradec Králové", "on_min": 352, "on_ortg": 118.0, "on_drtg": 129.6, "on_net": -11.6, "off_min": 316, "off_ortg": 107.3, "off_drtg": 122.0, "off_net": -14.7, "delta_net": 3.1}, {"first_name": "Ahmad", "family_name": "Rand", "slug": "bk-armex-energy-decin-ahmad-rand", "season": "2025-26", "team": "BK ARMEX ENERGY Děčín", "on_min": 192, "on_ortg": 108.9, "on_drtg": 120.7, "on_net": -11.8, "off_min": 322, "off_ortg": 120.3, "off_drtg": 124.7, "off_net": -4.4, "delta_net": -7.4}, {"first_name": "Matěj", "family_name": "Burda", "slug": "srsni-photomate-pisek-matej-burda", "season": "2025-26", "team": "Sršni Photomate Písek", "on_min": 426, "on_ortg": 115.6, "on_drtg": 127.5, "on_net": -11.9, "off_min": 303, "off_ortg": 133.0, "off_drtg": 111.5, "off_net": 21.5, "delta_net": -33.4}, {"first_name": "Kameron Jamal", "family_name": "Chatman", "slug": "bk-gapa-hradec-kralove-kameron-jamal-chatman", "season": "2025-26", "team": "BK GAPA Hradec Králové", "on_min": 681, "on_ortg": 115.0, "on_drtg": 127.5, "on_net": -12.5, "off_min": 300, "off_ortg": 100.5, "off_drtg": 126.6, "off_net": -26.1, "delta_net": 13.6}, {"first_name": "Matěj", "family_name": "Šafařík", "slug": "usk-praha-matej-safarik", "season": "2025-26", "team": "USK Praha", "on_min": 730, "on_ortg": 111.9, "on_drtg": 124.4, "on_net": -12.5, "off_min": 404, "off_ortg": 120.7, "off_drtg": 126.2, "off_net": -5.5, "delta_net": -7.0}, {"first_name": "Ricky Jamel", "family_name": "Clemons", "slug": "sk-slavia-praha-ricky-jamel-clemons", "season": "2025-26", "team": "SK Slavia Praha", "on_min": 12, "on_ortg": 104.9, "on_drtg": 117.4, "on_net": -12.5, "off_min": 28, "off_ortg": 139.7, "off_drtg": 122.9, "off_net": 16.8, "delta_net": -29.3}, {"first_name": "David", "family_name": "Škranc", "slug": "bk-gapa-hradec-kralove-david-skranc", "season": "2025-26", "team": "BK GAPA Hradec Králové", "on_min": 672, "on_ortg": 109.5, "on_drtg": 122.2, "on_net": -12.7, "off_min": 386, "off_ortg": 108.5, "off_drtg": 133.6, "off_net": -25.1, "delta_net": 12.4}, {"first_name": "Matyáš", "family_name": "Ježek", "slug": "sk-slavia-praha-matyas-jezek", "season": "2025-26", "team": "SK Slavia Praha", "on_min": 552, "on_ortg": 114.2, "on_drtg": 126.9, "on_net": -12.7, "off_min": 499, "off_ortg": 114.4, "off_drtg": 127.6, "off_net": -13.2, "delta_net": 0.5}, {"first_name": "Jonathan Leonard", "family_name": "Andre", "slug": "bk-olomoucko-jonathan-leonard-andre", "season": "2025-26", "team": "BK Olomoucko", "on_min": 673, "on_ortg": 116.2, "on_drtg": 129.0, "on_net": -12.8, "off_min": 279, "off_ortg": 101.5, "off_drtg": 117.5, "off_net": -16.0, "delta_net": 3.2}, {"first_name": "Nikolaos", "family_name": "Noumeros", "slug": "sk-slavia-praha-nikolaos-noumeros", "season": "2025-26", "team": "SK Slavia Praha", "on_min": 301, "on_ortg": 114.1, "on_drtg": 127.4, "on_net": -13.3, "off_min": 570, "off_ortg": 114.8, "off_drtg": 127.5, "off_net": -12.7, "delta_net": -0.6}, {"first_name": "Marek Ayers", "family_name": "Nelson", "slug": "bk-olomoucko-marek-ayers-nelson", "season": "2025-26", "team": "BK Olomoucko", "on_min": 667, "on_ortg": 108.9, "on_drtg": 122.5, "on_net": -13.6, "off_min": 364, "off_ortg": 113.9, "off_drtg": 123.7, "off_net": -9.8, "delta_net": -3.8}, {"first_name": "Michal", "family_name": "Svojanovský", "slug": "bk-kvis-pardubice-michal-svojanovsky", "season": "2025-26", "team": "BK KVIS Pardubice", "on_min": 21, "on_ortg": 132.3, "on_drtg": 146.2, "on_net": -13.9, "off_min": 209, "off_ortg": 141.0, "off_drtg": 98.5, "off_net": 42.5, "delta_net": -56.4}, {"first_name": "Martin", "family_name": "Roub", "slug": "bk-gapa-hradec-kralove-martin-roub", "season": "2025-26", "team": "BK GAPA Hradec Králové", "on_min": 713, "on_ortg": 112.8, "on_drtg": 126.9, "on_net": -14.1, "off_min": 384, "off_ortg": 104.2, "off_drtg": 123.2, "off_net": -19.0, "delta_net": 4.9}, {"first_name": "Lukáš", "family_name": "Feštr", "slug": "bk-armex-energy-decin-lukas-festr", "season": "2025-26", "team": "BK ARMEX ENERGY Děčín", "on_min": 488, "on_ortg": 112.5, "on_drtg": 126.7, "on_net": -14.2, "off_min": 657, "off_ortg": 121.4, "off_drtg": 112.1, "off_net": 9.3, "delta_net": -23.5}, {"first_name": "David", "family_name": "Böhm", "slug": "sk-slavia-praha-david-bohm", "season": "2025-26", "team": "SK Slavia Praha", "on_min": 859, "on_ortg": 114.7, "on_drtg": 128.9, "on_net": -14.2, "off_min": 232, "off_ortg": 115.3, "off_drtg": 122.3, "off_net": -7.0, "delta_net": -7.2}, {"first_name": "Ondřej", "family_name": "Švec", "slug": "usk-praha-ondrej-svec", "season": "2025-26", "team": "USK Praha", "on_min": 731, "on_ortg": 111.6, "on_drtg": 126.1, "on_net": -14.5, "off_min": 244, "off_ortg": 122.0, "off_drtg": 120.9, "off_net": 1.1, "delta_net": -15.6}, {"first_name": "Touko", "family_name": "Tainamo", "slug": "usk-praha-touko-tainamo", "season": "2025-26", "team": "USK Praha", "on_min": 735, "on_ortg": 111.4, "on_drtg": 126.5, "on_net": -15.1, "off_min": 399, "off_ortg": 122.0, "off_drtg": 122.2, "off_net": -0.2, "delta_net": -14.9}, {"first_name": "Adam", "family_name": "Goga", "slug": "bk-olomoucko-adam-goga", "season": "2025-26", "team": "BK Olomoucko", "on_min": 505, "on_ortg": 109.6, "on_drtg": 125.2, "on_net": -15.6, "off_min": 566, "off_ortg": 111.2, "off_drtg": 121.9, "off_net": -10.7, "delta_net": -4.9}, {"first_name": "Kareem Lamonte ", "family_name": "Brewton ", "slug": "bk-gapa-hradec-kralove-kareem-lamonte-brewton", "season": "2025-26", "team": "BK GAPA Hradec Králové", "on_min": 568, "on_ortg": 104.6, "on_drtg": 121.2, "on_net": -16.6, "off_min": 330, "off_ortg": 110.7, "off_drtg": 130.3, "off_net": -19.6, "delta_net": 3.0}, {"first_name": "Jakub", "family_name": "Šimonek", "slug": "srsni-photomate-pisek-jakub-simonek", "season": "2025-26", "team": "Sršni Photomate Písek", "on_min": 41, "on_ortg": 112.6, "on_drtg": 129.8, "on_net": -17.2, "off_min": 312, "off_ortg": 125.3, "off_drtg": 121.2, "off_net": 4.1, "delta_net": -21.3}, {"first_name": "Pavel", "family_name": "Czudek", "slug": "bk-opava-pavel-czudek", "season": "2025-26", "team": "BK Opava", "on_min": 7, "on_ortg": 121.0, "on_drtg": 138.4, "on_net": -17.4, "off_min": 151, "off_ortg": 150.8, "off_drtg": 115.4, "off_net": 35.4, "delta_net": -52.8}, {"first_name": "Jakub", "family_name": "Soldán", "slug": "usk-praha-jakub-soldan", "season": "2025-26", "team": "USK Praha", "on_min": 290, "on_ortg": 114.9, "on_drtg": 132.7, "on_net": -17.8, "off_min": 452, "off_ortg": 108.6, "off_drtg": 123.7, "off_net": -15.1, "delta_net": -2.7}, {"first_name": "Julian Thomas Tane", "family_name": "Roche", "slug": "nh-ostrava-julian-thomas-tane-roche", "season": "2025-26", "team": "NH Ostrava", "on_min": 110, "on_ortg": 113.5, "on_drtg": 131.3, "on_net": -17.8, "off_min": 127, "off_ortg": 107.4, "off_drtg": 126.0, "off_net": -18.6, "delta_net": 0.8}, {"first_name": "Dominik", "family_name": "Žák", "slug": "bk-olomoucko-dominik-zak", "season": "2025-26", "team": "BK Olomoucko", "on_min": 543, "on_ortg": 105.5, "on_drtg": 123.5, "on_net": -18.0, "off_min": 488, "off_ortg": 116.4, "off_drtg": 122.3, "off_net": -5.9, "delta_net": -12.1}, {"first_name": "Jiří", "family_name": "Svojanovský", "slug": "bk-olomoucko-jiri-svojanovsky", "season": "2025-26", "team": "BK Olomoucko", "on_min": 108, "on_ortg": 94.0, "on_drtg": 112.3, "on_net": -18.3, "off_min": 559, "off_ortg": 105.5, "off_drtg": 125.7, "off_net": -20.2, "delta_net": 1.9}, {"first_name": "Jakub", "family_name": "Mršťák", "slug": "sk-slavia-praha-jakub-mrstak", "season": "2025-26", "team": "SK Slavia Praha", "on_min": 10, "on_ortg": 157.2, "on_drtg": 175.5, "on_net": -18.3, "off_min": 67, "off_ortg": 103.0, "off_drtg": 135.4, "off_net": -32.4, "delta_net": 14.1}, {"first_name": "Pavel", "family_name": "Novák", "slug": "nh-ostrava-pavel-novak", "season": "2025-26", "team": "NH Ostrava", "on_min": 197, "on_ortg": 116.6, "on_drtg": 136.8, "on_net": -20.2, "off_min": 763, "off_ortg": 115.2, "off_drtg": 124.5, "off_net": -9.3, "delta_net": -10.9}, {"first_name": "Matija", "family_name": "Popović", "slug": "bk-gapa-hradec-kralove-matija-popovic", "season": "2025-26", "team": "BK GAPA Hradec Králové", "on_min": 310, "on_ortg": 105.7, "on_drtg": 127.0, "on_net": -21.3, "off_min": 240, "off_ortg": 102.1, "off_drtg": 127.9, "off_net": -25.8, "delta_net": 4.5}, {"first_name": "Lukáš", "family_name": "Dejmek", "slug": "usk-praha-lukas-dejmek", "season": "2025-26", "team": "USK Praha", "on_min": 112, "on_ortg": 104.7, "on_drtg": 127.0, "on_net": -22.3, "off_min": 508, "off_ortg": 108.1, "off_drtg": 123.5, "off_net": -15.4, "delta_net": -6.9}, {"first_name": "Tyrel Devonte", "family_name": "Bladen", "slug": "sk-slavia-praha-tyrel-devonte-bladen", "season": "2025-26", "team": "SK Slavia Praha", "on_min": 177, "on_ortg": 104.7, "on_drtg": 127.9, "on_net": -23.2, "off_min": 200, "off_ortg": 122.0, "off_drtg": 136.4, "off_net": -14.4, "delta_net": -8.8}, {"first_name": "Tomáš", "family_name": "Mikyska", "slug": "bk-gapa-hradec-kralove-tomas-mikyska", "season": "2025-26", "team": "BK GAPA Hradec Králové", "on_min": 107, "on_ortg": 101.7, "on_drtg": 125.0, "on_net": -23.3, "off_min": 285, "off_ortg": 103.7, "off_drtg": 124.7, "off_net": -21.0, "delta_net": -2.3}, {"first_name": "Esli", "family_name": "Edigin", "slug": "usk-praha-esli-edigin", "season": "2025-26", "team": "USK Praha", "on_min": 169, "on_ortg": 105.1, "on_drtg": 128.5, "on_net": -23.4, "off_min": 214, "off_ortg": 101.1, "off_drtg": 138.7, "off_net": -37.6, "delta_net": 14.2}, {"first_name": "Jordan", "family_name": "Glover", "slug": "sluneta-usti-nad-labem-jordan-glover", "season": "2025-26", "team": "SLUNETA  Ústí nad Labem", "on_min": 41, "on_ortg": 110.2, "on_drtg": 133.6, "on_net": -23.4, "off_min": 78, "off_ortg": 119.9, "off_drtg": 119.0, "off_net": 0.9, "delta_net": -24.3}, {"first_name": "Tomáš", "family_name": "Tkadlec", "slug": "bk-gapa-hradec-kralove-tomas-tkadlec", "season": "2025-26", "team": "BK GAPA Hradec Králové", "on_min": 96, "on_ortg": 84.8, "on_drtg": 108.9, "on_net": -24.1, "off_min": 492, "off_ortg": 108.9, "off_drtg": 135.1, "off_net": -26.2, "delta_net": 2.1}, {"first_name": "Jordan", "family_name": "Oupoh", "slug": "bk-olomoucko-jordan-oupoh", "season": "2025-26", "team": "BK Olomoucko", "on_min": 104, "on_ortg": 94.7, "on_drtg": 120.6, "on_net": -25.9, "off_min": 572, "off_ortg": 107.2, "off_drtg": 129.4, "off_net": -22.2, "delta_net": -3.7}, {"first_name": "Cody Chevell Christian", "family_name": "John", "slug": "bk-gapa-hradec-kralove-cody-chevell-christian-john", "season": "2025-26", "team": "BK GAPA Hradec Králové", "on_min": 140, "on_ortg": 110.3, "on_drtg": 136.8, "on_net": -26.5, "off_min": 53, "off_ortg": 115.1, "off_drtg": 106.5, "off_net": 8.6, "delta_net": -35.1}, {"first_name": "Alessandro", "family_name": "Petric", "slug": "bk-gapa-hradec-kralove-alessandro-petric", "season": "2025-26", "team": "BK GAPA Hradec Králové", "on_min": 213, "on_ortg": 112.1, "on_drtg": 138.8, "on_net": -26.7, "off_min": 297, "off_ortg": 102.0, "off_drtg": 118.1, "off_net": -16.1, "delta_net": -10.6}, {"first_name": "Samuel", "family_name": "Macht", "slug": "usk-praha-samuel-macht", "season": "2025-26", "team": "USK Praha", "on_min": 157, "on_ortg": 104.9, "on_drtg": 131.6, "on_net": -26.7, "off_min": 423, "off_ortg": 108.2, "off_drtg": 129.6, "off_net": -21.4, "delta_net": -5.3}, {"first_name": "Filip", "family_name": "Petružela", "slug": "sk-slavia-praha-filip-petruzela", "season": "2025-26", "team": "SK Slavia Praha", "on_min": 28, "on_ortg": 96.2, "on_drtg": 124.5, "on_net": -28.3, "off_min": 51, "off_ortg": 104.4, "off_drtg": 143.1, "off_net": -38.7, "delta_net": 10.4}, {"first_name": "Austin Calvin", "family_name": "Johnson", "slug": "bk-gapa-hradec-kralove-austin-calvin-johnson", "season": "2025-26", "team": "BK GAPA Hradec Králové", "on_min": 263, "on_ortg": 100.8, "on_drtg": 129.3, "on_net": -28.5, "off_min": 324, "off_ortg": 122.8, "off_drtg": 121.5, "off_net": 1.3, "delta_net": -29.8}, {"first_name": "Matyáš", "family_name": "Kraut", "slug": "sk-slavia-praha-matyas-kraut", "season": "2025-26", "team": "SK Slavia Praha", "on_min": 47, "on_ortg": 116.4, "on_drtg": 147.0, "on_net": -30.6, "off_min": 251, "off_ortg": 112.2, "off_drtg": 126.9, "off_net": -14.7, "delta_net": -15.9}, {"first_name": "Dalibor", "family_name": "Fait", "slug": "srsni-photomate-pisek-dalibor-fait", "season": "2025-26", "team": "Sršni Photomate Písek", "on_min": 8, "on_ortg": 87.5, "on_drtg": 119.5, "on_net": -32.0, "off_min": 31, "off_ortg": 114.7, "off_drtg": 99.0, "off_net": 15.7, "delta_net": -47.7}, {"first_name": "Jan", "family_name": "Bubeníček", "slug": "bk-gapa-hradec-kralove-jan-bubenicek", "season": "2025-26", "team": "BK GAPA Hradec Králové", "on_min": 278, "on_ortg": 99.2, "on_drtg": 131.9, "on_net": -32.7, "off_min": 508, "off_ortg": 112.8, "off_drtg": 124.5, "off_net": -11.7, "delta_net": -21.0}, {"first_name": "Radek", "family_name": "Pumprla", "slug": "sk-slavia-praha-radek-pumprla", "season": "2025-26", "team": "SK Slavia Praha", "on_min": 330, "on_ortg": 103.9, "on_drtg": 138.1, "on_net": -34.2, "off_min": 246, "off_ortg": 124.6, "off_drtg": 127.0, "off_net": -2.4, "delta_net": -31.8}, {"first_name": "Keyshaun Darrius", "family_name": "Langley", "slug": "pumpa-basket-brno-keyshaun-darrius-langley", "season": "2025-26", "team": "PUMPA Basket Brno", "on_min": 24, "on_ortg": 129.2, "on_drtg": 164.7, "on_net": -35.5, "off_min": 16, "off_ortg": 83.1, "off_drtg": 129.3, "off_net": -46.2, "delta_net": 10.7}, {"first_name": "Adam", "family_name": "Ivánek", "slug": "nh-ostrava-adam-ivanek", "season": "2025-26", "team": "NH Ostrava", "on_min": 45, "on_ortg": 97.7, "on_drtg": 133.7, "on_net": -36.0, "off_min": 289, "off_ortg": 107.8, "off_drtg": 130.8, "off_net": -23.0, "delta_net": -13.0}, {"first_name": "Miroslav", "family_name": "Kvapil", "slug": "bk-olomoucko-miroslav-kvapil", "season": "2025-26", "team": "BK Olomoucko", "on_min": 117, "on_ortg": 98.6, "on_drtg": 139.0, "on_net": -40.4, "off_min": 438, "off_ortg": 114.0, "off_drtg": 124.1, "off_net": -10.1, "delta_net": -30.3}, {"first_name": "Aleš", "family_name": "Jancur", "slug": "bk-gapa-hradec-kralove-ales-jancur", "season": "2025-26", "team": "BK GAPA Hradec Králové", "on_min": 12, "on_ortg": 62.4, "on_drtg": 102.9, "on_net": -40.5, "off_min": 223, "off_ortg": 99.8, "off_drtg": 145.0, "off_net": -45.2, "delta_net": 4.7}, {"first_name": "Adam", "family_name": "Kolář", "slug": "usk-praha-adam-kolar", "season": "2025-26", "team": "USK Praha", "on_min": 8, "on_ortg": 107.5, "on_drtg": 149.2, "on_net": -41.7, "off_min": 32, "off_ortg": 74.2, "off_drtg": 138.9, "off_net": -64.7, "delta_net": 23.0}, {"first_name": "Samuel", "family_name": "Wangle", "slug": "usk-praha-samuel-wangle", "season": "2025-26", "team": "USK Praha", "on_min": 8, "on_ortg": 110.3, "on_drtg": 152.2, "on_net": -41.9, "off_min": 71, "off_ortg": 122.7, "off_drtg": 126.7, "off_net": -4.0, "delta_net": -37.9}, {"first_name": "Matyáš", "family_name": "Janů", "slug": "nh-ostrava-matyas-janu", "season": "2025-26", "team": "NH Ostrava", "on_min": 46, "on_ortg": 83.5, "on_drtg": 127.4, "on_net": -43.9, "off_min": 305, "off_ortg": 110.0, "off_drtg": 137.1, "off_net": -27.1, "delta_net": -16.8}, {"first_name": "Ondřej", "family_name": "Petrák", "slug": "era-basketball-nymburk-ondrej-petrak", "season": "2025-26", "team": "ERA Basketball Nymburk", "on_min": 3, "on_ortg": 112.5, "on_drtg": 161.8, "on_net": -49.3, "off_min": 37, "off_ortg": 150.6, "off_drtg": 94.0, "off_net": 56.6, "delta_net": -105.9}, {"first_name": "Šimon", "family_name": "Čermák", "slug": "bk-olomoucko-simon-cermak", "season": "2025-26", "team": "BK Olomoucko", "on_min": 45, "on_ortg": 98.6, "on_drtg": 153.3, "on_net": -54.7, "off_min": 310, "off_ortg": 95.3, "off_drtg": 126.2, "off_net": -30.9, "delta_net": -23.8}, {"first_name": "Alexandr", "family_name": "Krob", "slug": "bk-armex-energy-decin-alexandr-krob", "season": "2025-26", "team": "BK ARMEX ENERGY Děčín", "on_min": 20, "on_ortg": 54.6, "on_drtg": 112.6, "on_net": -58.0, "off_min": 216, "off_ortg": 123.7, "off_drtg": 120.0, "off_net": 3.7, "delta_net": -61.7}, {"first_name": "Tevin Thomas", "family_name": "Olison", "slug": "pumpa-basket-brno-tevin-thomas-olison", "season": "2025-26", "team": "PUMPA Basket Brno", "on_min": 26, "on_ortg": 88.2, "on_drtg": 147.9, "on_net": -59.7, "off_min": 12, "off_ortg": 72.6, "off_drtg": 92.6, "off_net": -20.0, "delta_net": -39.7}, {"first_name": "Tomáš ", "family_name": "Rybařík", "slug": "srsni-photomate-pisek-tomas-rybarik", "season": "2025-26", "team": "Sršni Photomate Písek", "on_min": 2, "on_ortg": 0.0, "on_drtg": 71.2, "on_net": -71.2, "off_min": 77, "off_ortg": 127.6, "off_drtg": 111.3, "off_net": 16.3, "delta_net": -87.5}, {"first_name": "Marek", "family_name": "Půlpán", "slug": "bk-olomoucko-marek-pulpan", "season": "2025-26", "team": "BK Olomoucko", "on_min": 37, "on_ortg": 55.6, "on_drtg": 147.7, "on_net": -92.1, "off_min": 241, "off_ortg": 105.1, "off_drtg": 136.0, "off_net": -30.9, "delta_net": -61.2}, {"first_name": "Matěj", "family_name": "Žejdl", "slug": "srsni-photomate-pisek-matej-zejdl", "season": "2025-26", "team": "Sršni Photomate Písek", "on_min": 19, "on_ortg": 66.8, "on_drtg": 161.3, "on_net": -94.5, "off_min": 138, "off_ortg": 121.7, "off_drtg": 109.4, "off_net": 12.3, "delta_net": -106.8}, {"first_name": "Botond Oliver", "family_name": "Pavlík", "slug": "pumpa-basket-brno-botond-oliver-pavlik", "season": "2025-26", "team": "PUMPA Basket Brno", "on_min": 3, "on_ortg": 102.5, "on_drtg": 229.0, "on_net": -126.5, "off_min": 76, "off_ortg": 108.6, "off_drtg": 120.9, "off_net": -12.3, "delta_net": -114.2}, {"first_name": "Vojtěch", "family_name": "Martinek", "slug": "bk-gapa-hradec-kralove-vojtech-martinek", "season": "2025-26", "team": "BK GAPA Hradec Králové", "on_min": 2, "on_ortg": 108.7, "on_drtg": 247.7, "on_net": -139.0, "off_min": 77, "off_ortg": 110.8, "off_drtg": 106.7, "off_net": 4.1, "delta_net": -143.1}]